{
  "source_id": "2019-03-03-woo-besluit-bc-k-rapporten/2019-03-03-bijlage-72-claim-2017-november-onderzoek-naar-ad-hoc-afsluitingen-in-smf-waarvoor-wel-een-heronderzoek-is-gepland",
  "publication_slug": "2019-03-03-woo-besluit-bc-k-rapporten",
  "pdf_slug": "2019-03-03-bijlage-72-claim-2017-november-onderzoek-naar-ad-hoc-afsluitingen-in-smf-waarvoor-wel-een-heronderzoek-is-gepland",
  "source_page_url": "https://www.uwv.nl/nl/wet-open-overheid/woo-publicaties/2019/woo-besluit-bc-k-rapporten",
  "pdf_url": "https://www.uwv.nl/assets-kai/files/fd90f952-e43c-4f83-9114-a49b5cf289b0/bijlage-72-claim-2017-november-onderzoek-naar-ad-hoc-afsluitingen-in-smf-waarvoor-wel-een-heronderzoek-is-gepland.pdf",
  "publication_title": "Woo-besluit BC&K Rapporten",
  "publication_date": "2019-03-03T23:00:00Z",
  "publication_type": "WOO publicatie",
  "pdf_label": "Bijlage 72 Claim 2017 november onderzoek naar ad hoc afsluitingen in SMF waarvoor wel een heronderzoek is gepland (PDF, 256 kB)",
  "retrieved_at": "2026-06-30T14:22:43+00:00",
  "sha256": "b7286a5635cc81b08f37fd1b731cd8f28d9e2f97798f234c2ac8fc6d37ad2bd7",
  "page_count": 6,
  "ocr_used": false,
  "blocks": [
    {
      "type": "paragraph",
      "page": 1,
      "bbox": [
        181.25,
        317.17,
        449.63,
        329.17
      ],
      "text": "Onderzoek naar ad hoc afsluitingen in SMF",
      "source": "text"
    },
    {
      "type": "paragraph",
      "page": 1,
      "bbox": [
        181.25,
        331.93,
        449.38,
        343.93
      ],
      "text": "waarvoor wel een heronderzoek is gepland",
      "source": "text"
    },
    {
      "type": "heading",
      "page": 1,
      "bbox": [
        177.05,
        485.29,
        230.54,
        494.29
      ],
      "text": "SMZ-BC&K",
      "source": "text"
    },
    {
      "type": "paragraph",
      "page": 1,
      "bbox": [
        177.05,
        506.29,
        257.49,
        515.29
      ],
      "text": "November 2017",
      "source": "text"
    },
    {
      "type": "paragraph",
      "page": 2,
      "bbox": [
        518.76,
        787.96,
        524.48,
        796.96
      ],
      "text": "2",
      "source": "text"
    },
    {
      "type": "paragraph",
      "page": 2,
      "bbox": [
        70.82,
        798.68,
        344.9,
        806.72
      ],
      "text": "Onderzoek ad hoc afsluitingen in SMF Versie 1.0 22-11-2017",
      "source": "text"
    },
    {
      "type": "paragraph",
      "page": 3,
      "bbox": [
        88.82,
        72.97,
        381.59,
        84.01
      ],
      "text": "1. Achtergrond en aanleiding huidig onderzoek",
      "source": "text"
    },
    {
      "type": "paragraph",
      "page": 3,
      "bbox": [
        70.82,
        98.12,
        524.21,
        107.12
      ],
      "text": "Sinds de nieuwe SMF release van 26 augustus 2017 wordt een herbeoordeling afgedwongen bij een",
      "source": "text"
    },
    {
      "type": "paragraph",
      "page": 3,
      "bbox": [
        70.82,
        110.72,
        524.17,
        119.72
      ],
      "text": "uitkomst medisch 80 – 100%. In eerste instantie leek het erop dat in een aantal gevallen na een",
      "source": "text"
    },
    {
      "type": "paragraph",
      "page": 3,
      "bbox": [
        70.82,
        123.32,
        524.32,
        132.32
      ],
      "text": "herbeoordeling toch geen herbeoordeling te zijn gepland. Mogelijk zou hier sprake kunnen zijn van",
      "source": "text"
    },
    {
      "type": "paragraph",
      "page": 3,
      "bbox": [
        70.82,
        135.8,
        524.07,
        144.8
      ],
      "text": "een systeemprobleem. Bij nader inzien blijkt er toch een herbeoordeling te zijn gepland. Er zijn wat",
      "source": "text"
    },
    {
      "type": "paragraph",
      "page": 3,
      "bbox": [
        70.82,
        148.4,
        524.15,
        157.4
      ],
      "text": "dat betreft dus geen systeemproblemen. Voor deze gevallen werd echter de geplande",
      "source": "text"
    },
    {
      "type": "paragraph",
      "page": 3,
      "bbox": [
        70.82,
        161.12,
        225.06,
        170.12
      ],
      "text": "herbeoordeling ad hoc afgesloten.",
      "source": "text"
    },
    {
      "type": "paragraph",
      "page": 3,
      "bbox": [
        88.82,
        183.87,
        188.85,
        194.91
      ],
      "text": "2. Vraagstelling",
      "source": "text"
    },
    {
      "type": "paragraph",
      "page": 3,
      "bbox": [
        70.82,
        209.12,
        424.02,
        218.12
      ],
      "text": "Waarom worden de betreffende casussen ad hoc afgesloten en is dat terecht?",
      "source": "text"
    },
    {
      "type": "paragraph",
      "page": 3,
      "bbox": [
        88.82,
        231.87,
        183.42,
        242.91
      ],
      "text": "3. Bevindingen",
      "source": "text"
    },
    {
      "type": "paragraph",
      "page": 3,
      "bbox": [
        70.82,
        257.0,
        326.8,
        266.0
      ],
      "text": "Onderstaand de bevindingen op bsn niveau opgenomen.",
      "source": "text"
    },
    {
      "type": "paragraph",
      "page": 3,
      "bbox": [
        70.82,
        279.59,
        128.93,
        288.59
      ],
      "text": "0781.40.742",
      "source": "text"
    },
    {
      "type": "paragraph",
      "page": 3,
      "bbox": [
        70.82,
        290.51,
        520.25,
        299.51
      ],
      "text": "Op 14-09-2017 werd een herbeoordeling door VA afgerond. Conclusie van de VA is dat verbetering",
      "source": "text"
    },
    {
      "type": "paragraph",
      "page": 3,
      "bbox": [
        70.82,
        301.55,
        504.18,
        310.55
      ],
      "text": "te verwachten valt en er werd een herbeoordeling gepland over 1 jaar. Bij het afsluiten van het",
      "source": "text"
    },
    {
      "type": "paragraph",
      "page": 3,
      "bbox": [
        70.82,
        312.47,
        516.59,
        321.47
      ],
      "text": "product werd als herbeoordelingsdatum 01-09-2017 meegegeven. Op 30-10-2017 werd echter de",
      "source": "text"
    },
    {
      "type": "paragraph",
      "page": 3,
      "bbox": [
        70.82,
        323.39,
        488.48,
        332.39
      ],
      "text": "geplande herbeoordeling vanuit het voorportaal ad hoc afgesloten. De reden van het ad hoc",
      "source": "text"
    },
    {
      "type": "paragraph",
      "page": 3,
      "bbox": [
        70.82,
        334.31,
        506.69,
        343.31
      ],
      "text": "afsluiten is nergens te achterhalen. Mijns inziens had hier een herbeoordeling gepland dienen te",
      "source": "text"
    },
    {
      "type": "paragraph",
      "page": 3,
      "bbox": [
        70.82,
        345.23,
        188.3,
        354.23
      ],
      "text": "worden per 01-09-20018.",
      "source": "text"
    },
    {
      "type": "paragraph",
      "page": 3,
      "bbox": [
        70.82,
        367.19,
        128.93,
        376.19
      ],
      "text": "0812.41.963",
      "source": "text"
    },
    {
      "type": "paragraph",
      "page": 3,
      "bbox": [
        70.82,
        378.11,
        512.19,
        387.11
      ],
      "text": "Op 25-10-2017 werd een herbeoordeling door VA afgerond. Door de VA werd een herbeoordeling",
      "source": "text"
    },
    {
      "type": "paragraph",
      "page": 3,
      "bbox": [
        70.82,
        389.03,
        519.72,
        398.03
      ],
      "text": "gepland over 2 jaar. Dit is ook als zodanig opgenomen in SMF. De geplande herbeoordelingsdatum",
      "source": "text"
    },
    {
      "type": "paragraph",
      "page": 3,
      "bbox": [
        70.82,
        399.95,
        505.61,
        408.95
      ],
      "text": "valt echter na het bereiken van de AOW leeftijd om welke reden de geplande herbeoordeling ad",
      "source": "text"
    },
    {
      "type": "paragraph",
      "page": 3,
      "bbox": [
        70.82,
        410.87,
        492.28,
        419.87
      ],
      "text": "hoc werd afgesloten. Procesmatig had er echter een herbeoordeling per 01-01-2030 gepland",
      "source": "text"
    },
    {
      "type": "paragraph",
      "page": 3,
      "bbox": [
        70.82,
        421.79,
        368.08,
        430.79
      ],
      "text": "dienen te worden. Casus is derhalve onterecht ad hoc afgesloten.",
      "source": "text"
    },
    {
      "type": "paragraph",
      "page": 3,
      "bbox": [
        70.82,
        443.75,
        128.93,
        452.75
      ],
      "text": "0945.54.985",
      "source": "text"
    },
    {
      "type": "paragraph",
      "page": 3,
      "bbox": [
        70.82,
        454.67,
        516.64,
        463.67
      ],
      "text": "VA onderzoek van oktober 2017. Uit het VA onderzoek blijkt dat er momenteel geen sprake is van",
      "source": "text"
    },
    {
      "type": "paragraph",
      "page": 3,
      "bbox": [
        70.82,
        465.61,
        507.51,
        474.61
      ],
      "text": "duurzaamheid van de arbeidsbeperkingen. Een herbeoordeling zal worden gepland voor oktober",
      "source": "text"
    },
    {
      "type": "paragraph",
      "page": 3,
      "bbox": [
        70.82,
        476.53,
        515.23,
        485.53
      ],
      "text": "2018. Bij het afronden van het product werd als herbeoordelingsdatum 01-01-2018 meegegeven.",
      "source": "text"
    },
    {
      "type": "paragraph",
      "page": 3,
      "bbox": [
        70.82,
        487.45,
        499.92,
        496.45
      ],
      "text": "Deze herbeoordeling werd terecht ad hoc afgesloten. Een nieuwe herbeoordeling met de juiste",
      "source": "text"
    },
    {
      "type": "paragraph",
      "page": 3,
      "bbox": [
        70.82,
        498.37,
        301.17,
        507.37
      ],
      "text": "datum (i.c. 01-10-2018) kom ik niet tegen in SMF.",
      "source": "text"
    },
    {
      "type": "paragraph",
      "page": 3,
      "bbox": [
        70.82,
        520.33,
        128.96,
        529.33
      ],
      "text": "1196.69.614",
      "source": "text"
    },
    {
      "type": "paragraph",
      "page": 3,
      "bbox": [
        70.82,
        531.25,
        504.37,
        540.25
      ],
      "text": "Klant krijgt na VA en AD onderzoek met ingang van 11-10-2017 een WGA uitkering toegekend.",
      "source": "text"
    },
    {
      "type": "paragraph",
      "page": 3,
      "bbox": [
        70.82,
        542.17,
        496.2,
        551.17
      ],
      "text": "Klant wordt echter met ingang van 20-11-2017 voor <35% arbeidsongeschikt beschouwd om",
      "source": "text"
    },
    {
      "type": "paragraph",
      "page": 3,
      "bbox": [
        70.82,
        553.09,
        522.65,
        562.09
      ],
      "text": "welke reden de uitkering wordt ingetrokken. Voor het genoemde bsn kom ik overigens geen ad hoc",
      "source": "text"
    },
    {
      "type": "paragraph",
      "page": 3,
      "bbox": [
        70.82,
        564.01,
        211.31,
        573.01
      ],
      "text": "afgesloten casus in SMF tegen.",
      "source": "text"
    },
    {
      "type": "paragraph",
      "page": 3,
      "bbox": [
        70.82,
        574.93,
        515.41,
        583.93
      ],
      "text": "Voor dit bsn is er op 19-09-2017 een casus, WIA herbo verzoek klant, gecreëerd welke op 29-09-",
      "source": "text"
    },
    {
      "type": "paragraph",
      "page": 3,
      "bbox": [
        70.82,
        585.97,
        523.84,
        594.97
      ],
      "text": "2017 regulier is afgesloten. Bij het afsluiten van deze casus is de vereiste herbeoordelingsdatum op",
      "source": "text"
    },
    {
      "type": "paragraph",
      "page": 3,
      "bbox": [
        70.82,
        596.89,
        452.88,
        605.89
      ],
      "text": "29-09-2017 gezet. Als reden afsluiten is meegegeven WGA 80 – 100% AO-Medisch.",
      "source": "text"
    },
    {
      "type": "paragraph",
      "page": 3,
      "bbox": [
        70.82,
        607.81,
        522.41,
        616.81
      ],
      "text": "Vervolgens is er op 29-09-2017 een casus, WIA herbo VA, gecreëerd welke op 29-09-2017 regulier",
      "source": "text"
    },
    {
      "type": "paragraph",
      "page": 3,
      "bbox": [
        70.82,
        618.73,
        519.24,
        627.73
      ],
      "text": "is afgesloten. Bij het afsluiten van deze casus werd geen vereiste datum herbeoordeling gevraagd.",
      "source": "text"
    },
    {
      "type": "paragraph",
      "page": 3,
      "bbox": [
        70.82,
        629.65,
        284.58,
        638.65
      ],
      "text": "Als reden afsluiten is meegegeven Geen Recht.",
      "source": "text"
    },
    {
      "type": "paragraph",
      "page": 3,
      "bbox": [
        70.82,
        651.49,
        128.93,
        660.49
      ],
      "text": "1497.21.286",
      "source": "text"
    },
    {
      "type": "paragraph",
      "page": 3,
      "bbox": [
        70.82,
        662.56,
        517.99,
        671.56
      ],
      "text": "In oktober 2017 vindt er een heronderzoek plaats op verzoek van de verzekeraar omdat er sprake",
      "source": "text"
    },
    {
      "type": "paragraph",
      "page": 3,
      "bbox": [
        70.82,
        673.48,
        522.53,
        682.48
      ],
      "text": "was van een werkhervatting. Dit verzoek dateert al van begin 2017. Nadien is er echter sprake van",
      "source": "text"
    },
    {
      "type": "paragraph",
      "page": 3,
      "bbox": [
        70.82,
        684.4,
        517.31,
        693.4
      ],
      "text": "een behandeling waardoor er sprake is van volledige arbeidsongeschiktheid op medische gronden.",
      "source": "text"
    },
    {
      "type": "paragraph",
      "page": 3,
      "bbox": [
        70.82,
        695.32,
        505.2,
        704.32
      ],
      "text": "Een heronderzoek wordt overwogen over een ½ jaar. Bij het afronden van het product werd als",
      "source": "text"
    },
    {
      "type": "paragraph",
      "page": 3,
      "bbox": [
        70.82,
        706.24,
        293.77,
        715.24
      ],
      "text": "herbeoordelingsdatum 01-01-2018 meegegeven.",
      "source": "text"
    },
    {
      "type": "paragraph",
      "page": 3,
      "bbox": [
        70.82,
        717.16,
        500.01,
        726.16
      ],
      "text": "Deze herbeoordeling werd terecht ad hoc afgesloten. Een nieuwe herbeoordeling met de juiste",
      "source": "text"
    },
    {
      "type": "paragraph",
      "page": 3,
      "bbox": [
        70.82,
        728.08,
        301.17,
        737.08
      ],
      "text": "datum (i.c. 01-04-2018) kom ik niet tegen in SMF.",
      "source": "text"
    },
    {
      "type": "paragraph",
      "page": 3,
      "bbox": [
        518.76,
        787.96,
        524.48,
        796.96
      ],
      "text": "3",
      "source": "text"
    },
    {
      "type": "paragraph",
      "page": 3,
      "bbox": [
        70.82,
        798.68,
        344.9,
        806.72
      ],
      "text": "Onderzoek ad hoc afsluitingen in SMF Versie 1.0 22-11-2017",
      "source": "text"
    },
    {
      "type": "paragraph",
      "page": 4,
      "bbox": [
        70.82,
        83.82,
        128.93,
        92.82
      ],
      "text": "1520.74.545",
      "source": "text"
    },
    {
      "type": "paragraph",
      "page": 4,
      "bbox": [
        70.82,
        94.76,
        516.67,
        103.76
      ],
      "text": "Op verzoek van SMZ locatie Tilburg is er door SMZ locatie Heerlen een herbeoordeling uitgevoerd.",
      "source": "text"
    },
    {
      "type": "paragraph",
      "page": 4,
      "bbox": [
        70.82,
        105.68,
        486.62,
        114.68
      ],
      "text": "Op 27-10-2017 werd de gevraagde herbeoordeling door VA afgerond. Door de VA werd een",
      "source": "text"
    },
    {
      "type": "paragraph",
      "page": 4,
      "bbox": [
        70.82,
        116.6,
        519.64,
        125.6
      ],
      "text": "herbeoordeling gepland over een ½ jaar. Dit werd ook als zodanig opgenomen in SMF. SMZ locatie",
      "source": "text"
    },
    {
      "type": "paragraph",
      "page": 4,
      "bbox": [
        70.82,
        127.52,
        514.84,
        136.52
      ],
      "text": "Heerlen sluit deze casus ad hoc af en verzoekt de SMZ locatie Tilburg de geplande herbeoordeling",
      "source": "text"
    },
    {
      "type": "paragraph",
      "page": 4,
      "bbox": [
        70.82,
        138.44,
        516.07,
        147.44
      ],
      "text": "op te nemen in SMF. De ad hoc afsluiting is mijns inziens terecht. SMZ locatie Tilburg dient echter",
      "source": "text"
    },
    {
      "type": "paragraph",
      "page": 4,
      "bbox": [
        70.82,
        149.36,
        269.55,
        158.36
      ],
      "text": "de herbeoordeling nog op te nemen in SMF.",
      "source": "text"
    },
    {
      "type": "paragraph",
      "page": 4,
      "bbox": [
        70.82,
        171.32,
        128.93,
        180.32
      ],
      "text": "1540.78.050",
      "source": "text"
    },
    {
      "type": "paragraph",
      "page": 4,
      "bbox": [
        70.82,
        182.24,
        518.51,
        191.24
      ],
      "text": "Betreffende casus is opgevoerd onder een WIA product. Klant ontvangt echter een WAO-uitkering.",
      "source": "text"
    },
    {
      "type": "paragraph",
      "page": 4,
      "bbox": [
        70.82,
        193.16,
        515.46,
        202.16
      ],
      "text": "Op 12-09-2017 is er een herbeoordeling WAO afgerond. De VA plant geen herbeoordeling. Omdat",
      "source": "text"
    },
    {
      "type": "paragraph",
      "page": 4,
      "bbox": [
        70.82,
        204.08,
        505.25,
        213.08
      ],
      "text": "het product in SMF onder de WIA is opgevoerd is een herbeoordelingsdatum verplicht. Daar het",
      "source": "text"
    },
    {
      "type": "paragraph",
      "page": 4,
      "bbox": [
        70.82,
        215.0,
        495.86,
        224.0
      ],
      "text": "hier geen WIA maar een WAO betreft en de VA geen heronderzoek plant is de herbeoordeling",
      "source": "text"
    },
    {
      "type": "paragraph",
      "page": 4,
      "bbox": [
        70.82,
        226.04,
        189.23,
        235.04
      ],
      "text": "terecht ad hoc afgesloten.",
      "source": "text"
    },
    {
      "type": "paragraph",
      "page": 4,
      "bbox": [
        70.82,
        247.88,
        128.93,
        256.88
      ],
      "text": "1696.66.165",
      "source": "text"
    },
    {
      "type": "paragraph",
      "page": 4,
      "bbox": [
        70.82,
        258.8,
        505.89,
        267.8
      ],
      "text": "Klant ontvangt een uitkering op grond van hulpbehoevendheid tot 100%. Wij ontvangen van de",
      "source": "text"
    },
    {
      "type": "paragraph",
      "page": 4,
      "bbox": [
        70.82,
        269.72,
        503.37,
        278.72
      ],
      "text": "klant een bericht dat hij is opgenomen in een verpleeghuis. Aan de VA is gevraagd of klant nog",
      "source": "text"
    },
    {
      "type": "paragraph",
      "page": 4,
      "bbox": [
        70.82,
        280.67,
        513.43,
        289.67
      ],
      "text": "recht heeft op een verhoging uitkering wegens hulpbehoevendheid. Een herbeoordeling vond niet",
      "source": "text"
    },
    {
      "type": "paragraph",
      "page": 4,
      "bbox": [
        70.82,
        291.59,
        513.89,
        300.59
      ],
      "text": "plaats. De VA heeft alleen het dossier/de stukken even bekeken. Een heronderzoek werd dan ook",
      "source": "text"
    },
    {
      "type": "paragraph",
      "page": 4,
      "bbox": [
        70.82,
        302.63,
        523.88,
        311.63
      ],
      "text": "niet gepland. De uitkering van de klant is met ingang van 25-10-2013 omgezet naar een IVA. Mijns",
      "source": "text"
    },
    {
      "type": "paragraph",
      "page": 4,
      "bbox": [
        70.82,
        313.55,
        286.37,
        322.55
      ],
      "text": "inziens is deze casus terecht ad hoc afgesloten.",
      "source": "text"
    },
    {
      "type": "paragraph",
      "page": 4,
      "bbox": [
        70.82,
        335.39,
        128.93,
        344.39
      ],
      "text": "1703.65.359",
      "source": "text"
    },
    {
      "type": "paragraph",
      "page": 4,
      "bbox": [
        70.82,
        346.31,
        473.73,
        355.31
      ],
      "text": "Wij ontvangen van klant een verzoek tot verhoging wegens hulpbehoevendheid. VA doet",
      "source": "text"
    },
    {
      "type": "paragraph",
      "page": 4,
      "bbox": [
        70.82,
        357.23,
        493.76,
        366.23
      ],
      "text": "dossierstudie en neemt telefonisch contact op met de klant. Er is sprake van een situatie van",
      "source": "text"
    },
    {
      "type": "paragraph",
      "page": 4,
      "bbox": [
        70.82,
        368.15,
        505.99,
        377.15
      ],
      "text": "voortdurende oppas en verzorging en de uitkering wordt herzien naar 85%. Een herbeoordeling",
      "source": "text"
    },
    {
      "type": "paragraph",
      "page": 4,
      "bbox": [
        70.82,
        379.19,
        514.45,
        388.19
      ],
      "text": "voor klant werd niet gepland. De uitkering van de klant is met ingang van 10-06-2017 toegekend",
      "source": "text"
    },
    {
      "type": "paragraph",
      "page": 4,
      "bbox": [
        70.82,
        390.11,
        370.93,
        399.11
      ],
      "text": "als een IVA. Mijns inziens is deze casus terecht ad hoc afgesloten.",
      "source": "text"
    },
    {
      "type": "paragraph",
      "page": 4,
      "bbox": [
        70.82,
        411.95,
        128.96,
        420.95
      ],
      "text": "1965.04.193",
      "source": "text"
    },
    {
      "type": "paragraph",
      "page": 4,
      "bbox": [
        70.82,
        422.87,
        495.88,
        431.87
      ],
      "text": "Op verzoek van klant vindt er een VA beoordeling plaats. VA wil nog niet van een eindsituatie",
      "source": "text"
    },
    {
      "type": "paragraph",
      "page": 4,
      "bbox": [
        70.82,
        433.79,
        494.79,
        442.79
      ],
      "text": "praten en de prognose is onzeker. Datum herbeoordeling is ook niet aangegeven door de VA.",
      "source": "text"
    },
    {
      "type": "paragraph",
      "page": 4,
      "bbox": [
        70.82,
        444.71,
        517.5,
        453.71
      ],
      "text": "Klant is echter van mening dat er geen verbetering meer zal optreden. VA geeft aan dat klant zich",
      "source": "text"
    },
    {
      "type": "paragraph",
      "page": 4,
      "bbox": [
        70.82,
        457.19,
        482.16,
        466.19
      ],
      "text": "zal melden als er meer duidelijkheid is vanuit de behandeling welke klant ondergaat. Mijns",
      "source": "text"
    },
    {
      "type": "paragraph",
      "page": 4,
      "bbox": [
        70.82,
        469.81,
        508.35,
        478.81
      ],
      "text": "onterecht afgesloten. Gezien de verschillende zienswijze van de VA en de klant is het de vaag of",
      "source": "text"
    },
    {
      "type": "paragraph",
      "page": 4,
      "bbox": [
        70.82,
        482.53,
        176.76,
        491.53
      ],
      "text": "klant zich gaat melden.",
      "source": "text"
    },
    {
      "type": "paragraph",
      "page": 4,
      "bbox": [
        70.82,
        505.09,
        128.98,
        514.09
      ],
      "text": "2110.36.407",
      "source": "text"
    },
    {
      "type": "paragraph",
      "page": 4,
      "bbox": [
        70.82,
        516.01,
        518.33,
        525.01
      ],
      "text": "Door SMZ locatie Groningen is er een herbeoordeling afgerond. De VA acht een onderzoek naar de",
      "source": "text"
    },
    {
      "type": "paragraph",
      "page": 4,
      "bbox": [
        70.82,
        526.93,
        514.37,
        535.93
      ],
      "text": "arbeidsmogelijkheden zinvol. Te beginnen met het verzenden van een vragenformulier in februari",
      "source": "text"
    },
    {
      "type": "paragraph",
      "page": 4,
      "bbox": [
        70.82,
        537.97,
        510.62,
        546.97
      ],
      "text": "2018. Betreffende herbeoordeling werd ook gepland in SMF. De casus werd echter overgedragen",
      "source": "text"
    },
    {
      "type": "paragraph",
      "page": 4,
      "bbox": [
        70.82,
        548.89,
        509.75,
        557.89
      ],
      "text": "aan SMZ locatie Zwolle. SMZ locatie Zwolle sluit de betreffende casus mijns inziens onterecht af.",
      "source": "text"
    },
    {
      "type": "paragraph",
      "page": 4,
      "bbox": [
        70.82,
        570.73,
        128.93,
        579.73
      ],
      "text": "2270.95.376",
      "source": "text"
    },
    {
      "type": "paragraph",
      "page": 4,
      "bbox": [
        70.82,
        581.65,
        452.86,
        590.65
      ],
      "text": "Op verzoek van B@B werd een herbeoordeling gepland in verband met de mate van",
      "source": "text"
    },
    {
      "type": "paragraph",
      "page": 4,
      "bbox": [
        70.82,
        592.57,
        502.18,
        601.57
      ],
      "text": "arbeidsongeschiktheid per einde wachttijd. Klant is 61 jaar. De verwachting is dat de medische",
      "source": "text"
    },
    {
      "type": "paragraph",
      "page": 4,
      "bbox": [
        70.82,
        603.49,
        424.43,
        612.49
      ],
      "text": "situatie van klant op lange termijn wezenlijk zal verbeteren. Het ontstaan van",
      "source": "text"
    },
    {
      "type": "paragraph",
      "page": 4,
      "bbox": [
        70.82,
        614.53,
        521.38,
        623.53
      ],
      "text": "arbeidsmogelijkheden voor de pensioengerechtigde leeftijd is echter nauwelijks te verwachten. Een",
      "source": "text"
    },
    {
      "type": "paragraph",
      "page": 4,
      "bbox": [
        70.82,
        625.45,
        508.16,
        634.45
      ],
      "text": "heronderzoek is dan ook niet aan de orde. Mijns inziens is deze casus terecht ad hoc afgesloten.",
      "source": "text"
    },
    {
      "type": "paragraph",
      "page": 4,
      "bbox": [
        70.82,
        647.29,
        128.93,
        656.29
      ],
      "text": "2367.96.690",
      "source": "text"
    },
    {
      "type": "paragraph",
      "page": 4,
      "bbox": [
        70.82,
        658.24,
        508.04,
        667.24
      ],
      "text": "Op 14-09-2017 is de beoordeling einde wachttijd afgerond. Info werd opgevraagd ter aanvulling",
      "source": "text"
    },
    {
      "type": "paragraph",
      "page": 4,
      "bbox": [
        70.82,
        669.16,
        512.05,
        678.16
      ],
      "text": "van het dossier en het vaststellen van een termijn voor een heronderzoek. Op 04-10-2017 wordt",
      "source": "text"
    },
    {
      "type": "paragraph",
      "page": 4,
      "bbox": [
        70.82,
        680.2,
        511.48,
        689.2
      ],
      "text": "het dossier voorgelegd aan de VA omdat de gevraagde info niet wordt ontvangen omdat klant de",
      "source": "text"
    },
    {
      "type": "paragraph",
      "page": 4,
      "bbox": [
        70.82,
        691.12,
        480.04,
        700.12
      ],
      "text": "machtiging intrekt. Op 04-10-2017 is opnieuw een product in SMF opgevoerd ivm het niet",
      "source": "text"
    },
    {
      "type": "paragraph",
      "page": 4,
      "bbox": [
        70.82,
        702.04,
        511.64,
        711.04
      ],
      "text": "ontvangen van de info. De VA verwijst dan ook naar de eerdere einde wachttijd beoordeling. Een",
      "source": "text"
    },
    {
      "type": "paragraph",
      "page": 4,
      "bbox": [
        70.82,
        712.96,
        508.48,
        721.96
      ],
      "text": "datum heronderzoek werd dan ook niet gepland. Oorspronkelijk zou er een datum heronderzoek",
      "source": "text"
    },
    {
      "type": "paragraph",
      "page": 4,
      "bbox": [
        70.82,
        723.88,
        511.85,
        732.88
      ],
      "text": "gepland worden na ontvangst info. De info is niet ontvangen en mijns inziens had er dan wel een",
      "source": "text"
    },
    {
      "type": "paragraph",
      "page": 4,
      "bbox": [
        70.82,
        734.8,
        516.72,
        743.8
      ],
      "text": "datum heronderzoek gepland dienen te worden. Mijns inziens is herbeoordeling dan ook onterecht",
      "source": "text"
    },
    {
      "type": "paragraph",
      "page": 4,
      "bbox": [
        70.82,
        745.72,
        154.08,
        754.72
      ],
      "text": "ad hoc afgesloten.",
      "source": "text"
    },
    {
      "type": "paragraph",
      "page": 4,
      "bbox": [
        518.76,
        787.96,
        524.48,
        796.96
      ],
      "text": "4",
      "source": "text"
    },
    {
      "type": "paragraph",
      "page": 4,
      "bbox": [
        70.82,
        798.68,
        344.9,
        806.72
      ],
      "text": "Onderzoek ad hoc afsluitingen in SMF Versie 1.0 22-11-2017",
      "source": "text"
    },
    {
      "type": "paragraph",
      "page": 5,
      "bbox": [
        70.82,
        83.82,
        128.93,
        92.82
      ],
      "text": "2630.37.046",
      "source": "text"
    },
    {
      "type": "paragraph",
      "page": 5,
      "bbox": [
        70.82,
        94.64,
        524.0,
        103.64
      ],
      "text": "Herbeoordeling werd al gestart en afgerond in november 2016. Het product in SMF werd echter",
      "source": "text"
    },
    {
      "type": "paragraph",
      "page": 5,
      "bbox": [
        70.82,
        107.24,
        524.47,
        116.24
      ],
      "text": "niet afgesloten. In september 2017 wordt het dossier overgedragen van SMZ BZ naar SMZ",
      "source": "text"
    },
    {
      "type": "paragraph",
      "page": 5,
      "bbox": [
        70.82,
        119.72,
        524.14,
        128.72
      ],
      "text": "Eindhoven. Het product uit 2016 werd ad hoc afgesloten en vanwege de herbeoordeling uit 2016",
      "source": "text"
    },
    {
      "type": "paragraph",
      "page": 5,
      "bbox": [
        70.82,
        132.32,
        524.12,
        141.32
      ],
      "text": "nogmaals opgevoerd en regulier afgesloten. Hierdoor werd de opvoer van een herbeoordeling",
      "source": "text"
    },
    {
      "type": "paragraph",
      "page": 5,
      "bbox": [
        70.82,
        144.92,
        524.41,
        153.92
      ],
      "text": "verplicht. Deze was ook gepland voor oktober 2017. Omdat SMZ BZ het dossier overdraagt aan",
      "source": "text"
    },
    {
      "type": "paragraph",
      "page": 5,
      "bbox": [
        70.82,
        157.52,
        524.19,
        166.52
      ],
      "text": "SMZ Eindhoven is door SMZ BZ het product terecht ad hoc afgesloten. Middels een wintersignaal is",
      "source": "text"
    },
    {
      "type": "paragraph",
      "page": 5,
      "bbox": [
        70.82,
        170.12,
        524.11,
        179.12
      ],
      "text": "aan SMZ Eindhoven gevraagd het product op te voeren. SMZ Eindhoven heeft dit echter (nog) niet",
      "source": "text"
    },
    {
      "type": "paragraph",
      "page": 5,
      "bbox": [
        70.82,
        182.72,
        107.2,
        191.72
      ],
      "text": "gedaan.",
      "source": "text"
    },
    {
      "type": "paragraph",
      "page": 5,
      "bbox": [
        88.82,
        238.35,
        165.94,
        249.39
      ],
      "text": "4. Conclusie",
      "source": "text"
    },
    {
      "type": "paragraph",
      "page": 5,
      "bbox": [
        70.82,
        263.6,
        341.55,
        272.6
      ],
      "text": "Van de 14 onderzochte casussen zijn er naar mijn mening :",
      "source": "text"
    },
    {
      "type": "paragraph",
      "page": 5,
      "bbox": [
        70.82,
        286.19,
        414.4,
        295.19
      ],
      "text": "Terecht ad hoc afgesloten ivm WAO : 1 bsn",
      "source": "text"
    },
    {
      "type": "paragraph",
      "page": 5,
      "bbox": [
        70.82,
        297.11,
        414.36,
        306.11
      ],
      "text": "Terecht ad hoc afgesloten ivm IVA : 3 bsn",
      "source": "text"
    },
    {
      "type": "paragraph",
      "page": 5,
      "bbox": [
        70.82,
        308.03,
        414.36,
        317.03
      ],
      "text": "Terecht ad hoc afgesloten echter nieuwe opvoer ontbreekt : 4 bsn",
      "source": "text"
    },
    {
      "type": "paragraph",
      "page": 5,
      "bbox": [
        70.82,
        318.95,
        414.4,
        327.95
      ],
      "text": "Onterecht ad hoc afgesloten : 5 bsn",
      "source": "text"
    },
    {
      "type": "paragraph",
      "page": 5,
      "bbox": [
        70.82,
        329.87,
        414.36,
        338.87
      ],
      "text": "Niet van toepassing wegens <35% : 1 bsn",
      "source": "text"
    },
    {
      "type": "paragraph",
      "page": 5,
      "bbox": [
        518.76,
        787.96,
        524.48,
        796.96
      ],
      "text": "5",
      "source": "text"
    },
    {
      "type": "paragraph",
      "page": 5,
      "bbox": [
        70.82,
        798.68,
        344.9,
        806.72
      ],
      "text": "Onderzoek ad hoc afsluitingen in SMF Versie 1.0 22-11-2017",
      "source": "text"
    },
    {
      "type": "paragraph",
      "page": 6,
      "bbox": [
        153.62,
        298.67,
        191.92,
        307.67
      ],
      "text": "Colofon",
      "source": "text"
    },
    {
      "type": "paragraph",
      "page": 6,
      "bbox": [
        153.62,
        343.79,
        294.02,
        352.79
      ],
      "text": "Uitgever SMZ BC&K",
      "source": "text"
    },
    {
      "type": "paragraph",
      "page": 6,
      "bbox": [
        153.62,
        389.03,
        299.88,
        398.03
      ],
      "text": "Datum 22-11-2017",
      "source": "text"
    },
    {
      "type": "paragraph",
      "page": 6,
      "bbox": [
        153.62,
        411.59,
        260.53,
        420.59
      ],
      "text": "Versie 1.0",
      "source": "text"
    },
    {
      "type": "paragraph",
      "page": 6,
      "bbox": [
        153.62,
        434.15,
        416.14,
        443.15
      ],
      "text": "Document Onderzoek ad hoc afsluitingen in SMF",
      "source": "text"
    },
    {
      "type": "heading",
      "page": 6,
      "bbox": [
        150.14,
        501.95,
        191.05,
        508.01
      ],
      "text": " 2017, UWV",
      "source": "text"
    },
    {
      "type": "paragraph",
      "page": 6,
      "bbox": [
        150.14,
        520.43,
        434.82,
        526.43
      ],
      "text": "Alle rechten voorbehouden. Niets uit deze uitgave mag worden verveelvoudigd, opgeslagen in",
      "source": "text"
    },
    {
      "type": "paragraph",
      "page": 6,
      "bbox": [
        150.14,
        528.83,
        431.31,
        534.83
      ],
      "text": "een geautomatiseerd gegevensbestand, of openbaar gemaakt, in enige vorm, of enige wijze,",
      "source": "text"
    },
    {
      "type": "paragraph",
      "page": 6,
      "bbox": [
        150.14,
        537.35,
        429.51,
        543.35
      ],
      "text": "hetzij elektronisch, mechanisch, door fotokopieën, opnamen of enige andere manier, zonder",
      "source": "text"
    },
    {
      "type": "paragraph",
      "page": 6,
      "bbox": [
        150.14,
        545.87,
        301.62,
        551.87
      ],
      "text": "voorafgaande schriftelijke toestemming van UWV.",
      "source": "text"
    },
    {
      "type": "paragraph",
      "page": 6,
      "bbox": [
        518.76,
        787.96,
        524.48,
        796.96
      ],
      "text": "6",
      "source": "text"
    },
    {
      "type": "paragraph",
      "page": 6,
      "bbox": [
        70.82,
        798.68,
        344.9,
        806.72
      ],
      "text": "Onderzoek ad hoc afsluitingen in SMF Versie 1.0 22-11-2017",
      "source": "text"
    }
  ]
}
