{
  "source_id": "2022-11-30-besluit-woo-verzoek-tolkentarieven/2022-11-30-bijlage-57-20190218-3-20190218-indexering-uwv-normbedragen-voorzieningen-2019",
  "publication_slug": "2022-11-30-besluit-woo-verzoek-tolkentarieven",
  "pdf_slug": "2022-11-30-bijlage-57-20190218-3-20190218-indexering-uwv-normbedragen-voorzieningen-2019",
  "source_page_url": "https://www.uwv.nl/nl/wet-open-overheid/woo-publicaties/2022/besluit-woo-verzoek-tolkentarieven",
  "pdf_url": "https://www.uwv.nl/assets-kai/files/7529879a-e466-4f68-b4fc-aa1a1a6fa1b8/bijlage-57-20190218-3-20190218-indexering-uwv-normbedragen-voorzieningen-2019.pdf",
  "publication_title": "Besluit Woo-verzoek Tolkentarieven",
  "publication_date": "2022-11-30T00:00:00Z",
  "publication_type": "WOO publicatie",
  "pdf_label": "Bijlage 57. 20190218 3 20190218 Indexering UWV normbedragen voorzieningen 2019 (PDF, 294 kB)",
  "retrieved_at": "2026-06-30T13:52:43+00:00",
  "sha256": "27be6119db675e8965e6e63bf583062d26016301b7a2ceddccea1ca4f78772f1",
  "page_count": 3,
  "ocr_used": true,
  "blocks": [
    {
      "type": "heading",
      "page": 1,
      "bbox": [
        1122.0,
        42.0,
        1451.0,
        87.0
      ],
      "text": "BIJLAGE 57",
      "source": "ocr"
    },
    {
      "type": "heading",
      "page": 1,
      "bbox": [
        157.0,
        106.0,
        1347.0,
        158.0
      ],
      "text": "UWwV Voorlegger vergadering Raad van Bestuur UWV",
      "source": "ocr"
    },
    {
      "type": "paragraph",
      "page": 1,
      "bbox": [
        552.0,
        214.0,
        885.0,
        234.0
      ],
      "text": "Vergadering Raad van Bestuur",
      "source": "ocr"
    },
    {
      "type": "paragraph",
      "page": 1,
      "bbox": [
        139.0,
        270.0,
        203.0,
        284.0
      ],
      "text": "Datum",
      "source": "ocr"
    },
    {
      "type": "heading",
      "page": 1,
      "bbox": [
        133.0,
        314.0,
        1149.0,
        344.0
      ],
      "text": "Agendapunt Agendapunt Nummer",
      "source": "ocr"
    },
    {
      "type": "heading",
      "page": 1,
      "bbox": [
        138.0,
        361.0,
        1189.0,
        394.0
      ],
      "text": "Onderwerp Wijziging UWV-Normbedragen voorzieningen 2019",
      "source": "ocr"
    },
    {
      "type": "heading",
      "page": 1,
      "bbox": [
        135.0,
        412.0,
        704.0,
        445.0
      ],
      "text": "Directeur C.P. Thissen",
      "source": "ocr"
    },
    {
      "type": "heading",
      "page": 1,
      "bbox": [
        134.0,
        460.0,
        719.0,
        497.0
      ],
      "text": "opsteller art. 5.1lid2e",
      "source": "ocr"
    },
    {
      "type": "paragraph",
      "page": 1,
      "bbox": [
        139.0,
        517.0,
        750.0,
        537.0
      ],
      "text": "Portefeuillehouder RB G. van Weelden",
      "source": "ocr"
    },
    {
      "type": "paragraph",
      "page": 1,
      "bbox": [
        139.0,
        587.0,
        671.0,
        614.0
      ],
      "text": "Directeur Toelichting",
      "source": "ocr"
    },
    {
      "type": "heading",
      "page": 1,
      "bbox": [
        139.0,
        636.0,
        172.0,
        655.0
      ],
      "text": "BZ",
      "source": "ocr"
    },
    {
      "type": "heading",
      "page": 1,
      "bbox": [
        139.0,
        686.0,
        185.0,
        705.0
      ],
      "text": "FEZ",
      "source": "ocr"
    },
    {
      "type": "paragraph",
      "page": 1,
      "bbox": [
        139.0,
        834.0,
        604.0,
        849.0
      ],
      "text": "Door Raad van bestuur te nemen besluiten",
      "source": "ocr"
    },
    {
      "type": "paragraph",
      "page": 1,
      "bbox": [
        139.0,
        899.0,
        1545.0,
        924.0
      ],
      "text": "De Raad van Bestuur wordt verzocht in te stemmen met de indexering van de huidige normbedragen die tot de",
      "source": "ocr"
    },
    {
      "type": "paragraph",
      "page": 1,
      "bbox": [
        139.0,
        928.0,
        1567.0,
        954.0
      ],
      "text": "beleidsverantwoordelijkheid behoren van UWV, conform de door het CEBEON geadviseerde prijsindexcijfers per 1",
      "source": "ocr"
    },
    {
      "type": "paragraph",
      "page": 1,
      "bbox": [
        138.0,
        960.0,
        272.0,
        986.0
      ],
      "text": "april 2019.",
      "source": "ocr"
    },
    {
      "type": "paragraph",
      "page": 1,
      "bbox": [
        197.0,
        1030.0,
        441.0,
        1050.0
      ],
      "text": "Aanleiding en voorstel",
      "source": "ocr"
    },
    {
      "type": "paragraph",
      "page": 1,
      "bbox": [
        136.0,
        1095.0,
        525.0,
        1120.0
      ],
      "text": "Aanleiding en uiteenzetting",
      "source": "ocr"
    },
    {
      "type": "paragraph",
      "page": 1,
      "bbox": [
        190.0,
        1156.0,
        920.0,
        1182.0
      ],
      "text": "1. Deels geïndexeerde normbedragen per i januari 2019",
      "source": "ocr"
    },
    {
      "type": "paragraph",
      "page": 1,
      "bbox": [
        237.0,
        1187.0,
        1381.0,
        1212.0
      ],
      "text": "UWV is gewoon om jaarlijks - per 1 januari - de normbedragen voorzieningen te indexeren",
      "source": "ocr"
    },
    {
      "type": "paragraph",
      "page": 1,
      "bbox": [
        236.0,
        1217.0,
        1488.0,
        1243.0
      ],
      "text": "overeenkomstig het geldende CBS-prijsindexcijfer. Per 1 januari 2019 heeft er echter een beperkte",
      "source": "ocr"
    },
    {
      "type": "paragraph",
      "page": 1,
      "bbox": [
        237.0,
        1246.0,
        1349.0,
        1272.0
      ],
      "text": "indexering plaatsgevonden. Het betrof uitsluitend een indexering van de normbedragen:",
      "source": "ocr"
    },
    {
      "type": "paragraph",
      "page": 1,
      "bbox": [
        236.0,
        1277.0,
        939.0,
        1302.0
      ],
      "text": "a. die zijn gebaseerd op het wettelijk minimumloon en",
      "source": "ocr"
    },
    {
      "type": "paragraph",
      "page": 1,
      "bbox": [
        237.0,
        1308.0,
        1328.0,
        1333.0
      ],
      "text": "b. die het - door het Ministerie SZW vastgestelde - indexcijfer starterskrediet volgen.",
      "source": "ocr"
    },
    {
      "type": "paragraph",
      "page": 1,
      "bbox": [
        237.0,
        1338.0,
        1087.0,
        1364.0
      ],
      "text": "Deze normbedragen zijn verhoogd t.0.v. de situatie 1 januari 2018.",
      "source": "ocr"
    },
    {
      "type": "paragraph",
      "page": 1,
      "bbox": [
        237.0,
        1399.0,
        1470.0,
        1425.0
      ],
      "text": "De normbedragen die tot de beleidsbevoegdheid van UWV behoren (hierna “UWV-normbedragen”",
      "source": "ocr"
    },
    {
      "type": "paragraph",
      "page": 1,
      "bbox": [
        236.0,
        1430.0,
        1528.0,
        1455.0
      ],
      "text": "genoemd), zijn hangende besluitvorming/implementatie rondom de uitkomsten van het zgn. CEBEON-",
      "source": "ocr"
    },
    {
      "type": "paragraph",
      "page": 1,
      "bbox": [
        236.0,
        1460.0,
        1518.0,
        1486.0
      ],
      "text": "onderzoek - (nog) niet geïndexeerd. De Raad van Bestuur heeft op 27 november jl. deze handelwijze",
      "source": "ocr"
    },
    {
      "type": "paragraph",
      "page": 1,
      "bbox": [
        236.0,
        1490.0,
        1548.0,
        1515.0
      ],
      "text": "vastgesteld. De per 1 januari 2019 geldende normbedragen zijn in een Wijzigingsbesluit gepubliceerd in",
      "source": "ocr"
    },
    {
      "type": "paragraph",
      "page": 1,
      "bbox": [
        236.0,
        1520.0,
        457.0,
        1540.0
      ],
      "text": "de Staatscourant.",
      "source": "ocr"
    },
    {
      "type": "paragraph",
      "page": 1,
      "bbox": [
        189.0,
        1581.0,
        762.0,
        1607.0
      ],
      "text": "2. Handelwijze uitkomst CEBEON-onderzoek",
      "source": "ocr"
    },
    {
      "type": "paragraph",
      "page": 1,
      "bbox": [
        237.0,
        1612.0,
        1535.0,
        1637.0
      ],
      "text": "Het onderzoeksbureau CEBEON heeft — in opdracht van WERKbedrijf — in 2018 onderzoek gedaan naar",
      "source": "ocr"
    },
    {
      "type": "paragraph",
      "page": 1,
      "bbox": [
        236.0,
        1642.0,
        1516.0,
        1668.0
      ],
      "text": "0.a. de samenstelling en actualiteit van de normbedragen voorzieningen. Aanleiding hiervoor was dat",
      "source": "ocr"
    },
    {
      "type": "paragraph",
      "page": 1,
      "bbox": [
        237.0,
        1673.0,
        1533.0,
        1698.0
      ],
      "text": "UWV niet (meer) beschikte over een uitlegbare basis voor de normbedragen. In oktober heeft CEBEON",
      "source": "ocr"
    },
    {
      "type": "paragraph",
      "page": 1,
      "bbox": [
        236.0,
        1702.0,
        1468.0,
        1728.0
      ],
      "text": "zijn advies uitgebracht. Op 5 februari jl.is de Raad over het advies geïnformeerd. Door de Raad is",
      "source": "ocr"
    },
    {
      "type": "paragraph",
      "page": 1,
      "bbox": [
        237.0,
        1734.0,
        1440.0,
        1760.0
      ],
      "text": "besloten om de uitkomsten van het onderzoek, in één keer en in zijn geheel, te omarmen en te",
      "source": "ocr"
    },
    {
      "type": "paragraph",
      "page": 1,
      "bbox": [
        237.0,
        1763.0,
        1402.0,
        1789.0
      ],
      "text": "implementeren. Gelet op de (financiële) consequenties van het advies is afstemming met de",
      "source": "ocr"
    },
    {
      "type": "paragraph",
      "page": 1,
      "bbox": [
        236.0,
        1794.0,
        1529.0,
        1819.0
      ],
      "text": "opdrachtgevers; de Ministeries SZW, OCW en VWS vereist. Daarna worden belangenorganisaties zoals",
      "source": "ocr"
    },
    {
      "type": "paragraph",
      "page": 1,
      "bbox": [
        236.0,
        1824.0,
        1477.0,
        1850.0
      ],
      "text": "0.a. Tolkorganisaties, Oval/Noloc en cliëntenraden van de uitkomsten het onderzoek en de met de",
      "source": "ocr"
    },
    {
      "type": "paragraph",
      "page": 1,
      "bbox": [
        236.0,
        1855.0,
        1542.0,
        1880.0
      ],
      "text": "opdrachtgevers nader afgestemde handelwijze in kennis gesteld. Implementatie van de uitkomsten van",
      "source": "ocr"
    },
    {
      "type": "paragraph",
      "page": 1,
      "bbox": [
        237.0,
        1886.0,
        1068.0,
        1911.0
      ],
      "text": "het CEBEON-rapport is daarmee niet op korte termijn te voorzien.",
      "source": "ocr"
    },
    {
      "type": "paragraph",
      "page": 1,
      "bbox": [
        189.0,
        1947.0,
        716.0,
        1972.0
      ],
      "text": "3. Indexering van \"UWV-normbedragen”",
      "source": "ocr"
    },
    {
      "type": "paragraph",
      "page": 1,
      "bbox": [
        236.0,
        1977.0,
        1547.0,
        2003.0
      ],
      "text": "Omdat implementatie van het CEBEON-advies op zich laat wachten, is gekeken of de huidige wijze van",
      "source": "ocr"
    },
    {
      "type": "paragraph",
      "page": 1,
      "bbox": [
        237.0,
        2007.0,
        1573.0,
        2032.0
      ],
      "text": "indexeren leidt tot wijziging van de 'UWV-normbedragen” per 1 januari 2019. Immers anders dan voor de",
      "source": "ocr"
    },
    {
      "type": "paragraph",
      "page": 1,
      "bbox": [
        236.0,
        2037.0,
        1526.0,
        2062.0
      ],
      "text": "overige normbedragen is hiervoor nog geen indexeringspercentage berekend. Tot deze normbedragen",
      "source": "ocr"
    },
    {
      "type": "paragraph",
      "page": 1,
      "bbox": [
        237.0,
        2068.0,
        1538.0,
        2093.0
      ],
      "text": "behoren 0.a. de uurvergoeding van tolken, het tarief voor Jobcoaches en vergoedingen aan klanten om",
      "source": "ocr"
    },
    {
      "type": "paragraph",
      "page": 1,
      "bbox": [
        236.0,
        2098.0,
        640.0,
        2118.0
      ],
      "text": "van en naar het werk te komen.",
      "source": "ocr"
    },
    {
      "type": "paragraph",
      "page": 1,
      "bbox": [
        237.0,
        2159.0,
        1485.0,
        2185.0
      ],
      "text": "Hanteert UWV de huidige indexeringswijze, dan komt het indexeringspercentage uit op 0,9948. Dit",
      "source": "ocr"
    },
    {
      "type": "paragraph",
      "page": 1,
      "bbox": [
        237.0,
        2190.0,
        1545.0,
        2215.0
      ],
      "text": "percentage ligt onder de 1,00. Dit betekent dat de “UwV-normbedragen” in 2019 niet wijzigen t.0.v. de",
      "source": "ocr"
    },
    {
      "type": "paragraph",
      "page": 1,
      "bbox": [
        236.0,
        2219.0,
        1452.0,
        2245.0
      ],
      "text": "situatie 2018. Het beleid is namelijk dat de bedragen niet naar beneden worden bijgesteld. Voor",
      "source": "ocr"
    },
    {
      "type": "paragraph",
      "page": 1,
      "bbox": [
        79.0,
        2264.0,
        304.0,
        2278.0
      ],
      "text": "cCO140 22176 10-12 W",
      "source": "ocr"
    },
    {
      "type": "paragraph",
      "page": 2,
      "bbox": [
        413.69,
        32.18,
        422.98,
        42.09
      ],
      "text": "2e",
      "source": "text"
    },
    {
      "type": "paragraph",
      "page": 2,
      "bbox": [
        84.96,
        33.09,
        546.94,
        42.09
      ],
      "text": "leveranciers en gebruikers van voorzieningen betekent dit, dat voor het achtereenvolgende jaar de",
      "source": "text"
    },
    {
      "type": "paragraph",
      "page": 2,
      "bbox": [
        84.96,
        44.0,
        248.1,
        53.0
      ],
      "text": "normbedragen onveranderd blijven.",
      "source": "text"
    },
    {
      "type": "paragraph",
      "page": 2,
      "bbox": [
        84.96,
        65.84,
        556.59,
        74.84
      ],
      "text": "Het indexeringspercentage lag in 2018 namelijk ook onder de 1,00. Zij blijven dus op hetzelfde prijspeil",
      "source": "text"
    },
    {
      "type": "paragraph",
      "page": 2,
      "bbox": [
        84.96,
        76.76,
        534.74,
        85.76
      ],
      "text": "als 2017. Deze normbedragen zijn (zie onder paragraaf 1) in de Staatscourant gepubliceerd, in het",
      "source": "text"
    },
    {
      "type": "paragraph",
      "page": 2,
      "bbox": [
        84.96,
        87.67,
        562.15,
        96.67
      ],
      "text": "Wijzigingsbesluit normbedragen Voorzieningen 2019. Nadere actie zou dan niet meer zijn vereist, anders",
      "source": "text"
    },
    {
      "type": "paragraph",
      "page": 2,
      "bbox": [
        84.96,
        98.72,
        274.74,
        107.72
      ],
      "text": "dan de betrokken informaties informeren.",
      "source": "text"
    },
    {
      "type": "paragraph",
      "page": 2,
      "bbox": [
        67.56,
        120.57,
        444.69,
        129.57
      ],
      "text": "4. (On)wenselijkheid in stand houden ongewijzigde ‘UWV-normbedragen” in 2019",
      "source": "text"
    },
    {
      "type": "paragraph",
      "page": 2,
      "bbox": [
        84.96,
        131.49,
        527.62,
        140.49
      ],
      "text": "Echter, de huidige wijze van indexeren kent (forse) kritiek van in ieder geval de Tolkorganisaties.",
      "source": "text"
    },
    {
      "type": "paragraph",
      "page": 2,
      "bbox": [
        84.96,
        142.4,
        559.82,
        151.4
      ],
      "text": "Daarnaast hebben Oval én Noloc, in het operationeel brancheoverleg in februari jl., aangegeven, dat het",
      "source": "text"
    },
    {
      "type": "paragraph",
      "page": 2,
      "bbox": [
        84.96,
        153.32,
        561.55,
        162.32
      ],
      "text": "onvoorstelbaar zou zijn, als UWV het Jobcoachtarief niet alsnog zou indexeren – m.a.w. verhogen. En dit",
      "source": "text"
    },
    {
      "type": "paragraph",
      "page": 2,
      "bbox": [
        84.96,
        164.24,
        552.15,
        173.24
      ],
      "text": "bij voorkeur met terugwerkende kracht per 1 januari 2019. Temeer nu de uitkomsten van het CEBEON",
      "source": "text"
    },
    {
      "type": "paragraph",
      "page": 2,
      "bbox": [
        84.96,
        175.28,
        544.11,
        184.28
      ],
      "text": "onderzoek op zich laten wachten. UWV heeft aangegeven, te onderzoeken welke uitkomst de huidige",
      "source": "text"
    },
    {
      "type": "paragraph",
      "page": 2,
      "bbox": [
        84.96,
        186.2,
        205.01,
        195.2
      ],
      "text": "wijze van indexeren heeft.",
      "source": "text"
    },
    {
      "type": "paragraph",
      "page": 2,
      "bbox": [
        382.69,
        207.14,
        392.02,
        217.03
      ],
      "text": "2e",
      "source": "text"
    },
    {
      "type": "paragraph",
      "page": 2,
      "bbox": [
        84.96,
        208.03,
        564.63,
        217.05
      ],
      "text": "Nu de huidige handelwijze m.b.t. indexatie (opnieuw en voor het achtereenvolgende jaar) niet leidt tot",
      "source": "text"
    },
    {
      "type": "paragraph",
      "page": 2,
      "bbox": [
        84.96,
        218.96,
        519.2,
        227.96
      ],
      "text": "verhoging van de “UWV-normbedragen”, lijkt nog meer ontevredenheid voor de hand te liggen.",
      "source": "text"
    },
    {
      "type": "paragraph",
      "page": 2,
      "bbox": [
        84.96,
        229.88,
        553.31,
        238.88
      ],
      "text": "Voorstelbaar is dat in het bijzonder tolk- en Jobcoachorganisaties uiting aan hun ontevredenheid zullen",
      "source": "text"
    },
    {
      "type": "paragraph",
      "page": 2,
      "bbox": [
        84.96,
        240.92,
        115.6,
        249.92
      ],
      "text": "geven.",
      "source": "text"
    },
    {
      "type": "paragraph",
      "page": 2,
      "bbox": [
        67.56,
        262.77,
        132.65,
        271.77
      ],
      "text": "5. Alternatief",
      "source": "text"
    },
    {
      "type": "paragraph",
      "page": 2,
      "bbox": [
        84.96,
        273.69,
        535.32,
        282.69
      ],
      "text": "Een alternatief zou kunnen zijn, dat UWV in 2019 de suggestie overneemt van CEBEON t.a.v. de te",
      "source": "text"
    },
    {
      "type": "paragraph",
      "page": 2,
      "bbox": [
        84.96,
        284.6,
        500.1,
        293.6
      ],
      "text": "hanteren prijsindexcijfers voor de “UWV-normbedragen”. CEBEON stelt voor om een drietal",
      "source": "text"
    },
    {
      "type": "paragraph",
      "page": 2,
      "bbox": [
        84.95,
        295.52,
        275.42,
        304.52
      ],
      "text": "indexeringscijfers te gebruiken: te weten:",
      "source": "text"
    },
    {
      "type": "paragraph",
      "page": 2,
      "bbox": [
        84.95,
        306.44,
        253.33,
        315.44
      ],
      "text": "- Het consumentenprijsindexcijfer;",
      "source": "text"
    },
    {
      "type": "paragraph",
      "page": 2,
      "bbox": [
        84.95,
        317.48,
        266.46,
        326.48
      ],
      "text": "- Indexcijfer maximale premieloon en",
      "source": "text"
    },
    {
      "type": "paragraph",
      "page": 2,
      "bbox": [
        84.95,
        328.4,
        266.3,
        337.4
      ],
      "text": "- Indexcijfer CAO-lonen voor de zorg.",
      "source": "text"
    },
    {
      "type": "paragraph",
      "page": 2,
      "bbox": [
        84.94,
        350.23,
        544.34,
        359.23
      ],
      "text": "CEBEON heeft vervolgens de normbedragen ingedeeld, naar de meest logische van toepassing zijnde",
      "source": "text"
    },
    {
      "type": "paragraph",
      "page": 2,
      "bbox": [
        84.94,
        361.15,
        361.35,
        370.15
      ],
      "text": "prijsindexcijfer. Per 1 januari 2019 bedragen de indexcijfers:",
      "source": "text"
    },
    {
      "type": "paragraph",
      "page": 2,
      "bbox": [
        84.94,
        372.07,
        259.76,
        381.07
      ],
      "text": "- Consumentenprijsindexcijfer: 1,01",
      "source": "text"
    },
    {
      "type": "paragraph",
      "page": 2,
      "bbox": [
        84.94,
        382.98,
        294.18,
        391.98
      ],
      "text": "- Indexcijfer maximaal premieloon: 1,02 en",
      "source": "text"
    },
    {
      "type": "paragraph",
      "page": 2,
      "bbox": [
        84.94,
        394.03,
        229.7,
        403.03
      ],
      "text": "- Indexcijfer CAO-lonen 1,03.",
      "source": "text"
    },
    {
      "type": "paragraph",
      "page": 2,
      "bbox": [
        84.94,
        415.86,
        522.86,
        424.86
      ],
      "text": "Als UWV de voornoemde indexcijfers hanteert, dan zou dit in de hele breedte betekenen dat alle",
      "source": "text"
    },
    {
      "type": "paragraph",
      "page": 2,
      "bbox": [
        84.94,
        426.78,
        538.82,
        435.78
      ],
      "text": "normbedragen in 2019 worden verhoogd. De indexeringspercentages worden dan berekend over de",
      "source": "text"
    },
    {
      "type": "paragraph",
      "page": 2,
      "bbox": [
        84.94,
        437.69,
        550.23,
        446.69
      ],
      "text": "huidige normbedragen, dus (nog) niet over de door CEBEON geadviseerde normbedragen. Zie voor de",
      "source": "text"
    },
    {
      "type": "paragraph",
      "page": 2,
      "bbox": [
        84.94,
        448.61,
        317.58,
        457.61
      ],
      "text": "uitkomst van de indexering de bijgevoegde bijlage.",
      "source": "text"
    },
    {
      "type": "paragraph",
      "page": 2,
      "bbox": [
        103.54,
        470.57,
        223.02,
        479.57
      ],
      "text": "a. Terugwerkende kracht",
      "source": "text"
    },
    {
      "type": "paragraph",
      "page": 2,
      "bbox": [
        84.93,
        492.41,
        566.21,
        501.41
      ],
      "text": "De branche dringt er op aan dat UWV – mocht er sprake zijn van een verhoging van het tarief – deze met",
      "source": "text"
    },
    {
      "type": "paragraph",
      "page": 2,
      "bbox": [
        84.94,
        503.32,
        548.29,
        512.32
      ],
      "text": "terugwerkende kracht per 1 januari 2019 te laten ingaan. Dit zou betekenen, dat UWV reeds betaalde",
      "source": "text"
    },
    {
      "type": "paragraph",
      "page": 2,
      "bbox": [
        84.94,
        514.24,
        561.43,
        523.24
      ],
      "text": "vergoedingen aan klanten en leveranciers opnieuw zou moeten berekenen op basis van nieuwe facturen.",
      "source": "text"
    },
    {
      "type": "paragraph",
      "page": 2,
      "bbox": [
        84.94,
        525.16,
        560.32,
        534.16
      ],
      "text": "Dit geeft een enorme administratieve last op zowel klanten/leveranciers als UWV. Daarbij komt dat UWV",
      "source": "text"
    },
    {
      "type": "paragraph",
      "page": 2,
      "bbox": [
        84.94,
        536.2,
        503.97,
        545.2
      ],
      "text": "niet gewoon is met terugwerkende krachten prijzen te herzien. Het hanteren van verhoogde",
      "source": "text"
    },
    {
      "type": "paragraph",
      "page": 2,
      "bbox": [
        84.94,
        547.12,
        382.27,
        556.12
      ],
      "text": "normbedragen met terugwerkende kracht is daarmee geen optie.",
      "source": "text"
    },
    {
      "type": "paragraph",
      "page": 2,
      "bbox": [
        84.94,
        568.95,
        538.73,
        577.95
      ],
      "text": "Mocht de Raad ervoor kiezen de indexcijfers zoals voorgesteld door CEBEON te hanteren, dan is het",
      "source": "text"
    },
    {
      "type": "paragraph",
      "page": 2,
      "bbox": [
        84.95,
        579.87,
        555.5,
        588.87
      ],
      "text": "voorstel om dit – per toekomende datum - per 1 april 2019 te doen. Het indexcijfer wordt toegepast op",
      "source": "text"
    },
    {
      "type": "paragraph",
      "page": 2,
      "bbox": [
        84.96,
        590.78,
        204.78,
        599.78
      ],
      "text": "de huidige normbedragen.",
      "source": "text"
    },
    {
      "type": "paragraph",
      "page": 2,
      "bbox": [
        67.56,
        612.81,
        122.58,
        621.81
      ],
      "text": "6. Voorstel",
      "source": "text"
    },
    {
      "type": "paragraph",
      "page": 2,
      "bbox": [
        84.96,
        623.73,
        565.55,
        632.73
      ],
      "text": "Ondanks dat de Raad op 5 februari jl. het besluit heeft genomen, het advies van CEBEON integraal in één",
      "source": "text"
    },
    {
      "type": "paragraph",
      "page": 2,
      "bbox": [
        84.96,
        634.64,
        547.13,
        643.64
      ],
      "text": "keer te implementeren, luidt het voorstel de ´UWV-normbedragen` toch op basis van de in dit advies",
      "source": "text"
    },
    {
      "type": "paragraph",
      "page": 2,
      "bbox": [
        84.96,
        645.56,
        519.03,
        654.56
      ],
      "text": "voorgestelde wijze te indexeren. De reden hiervoor is, dat we op deze manier zowel klanten als",
      "source": "text"
    },
    {
      "type": "paragraph",
      "page": 2,
      "bbox": [
        84.96,
        656.48,
        559.76,
        665.48
      ],
      "text": "leveranciers tegemoet komen door een lichte prijsverhoging van de normbedragen. Daarmee zorgt UWV",
      "source": "text"
    },
    {
      "type": "paragraph",
      "page": 2,
      "bbox": [
        84.96,
        667.39,
        538.41,
        676.39
      ],
      "text": "ook strategisch gezien voor rust. In deze periode van relatieve rust kan dan de verdere dialoog met",
      "source": "text"
    },
    {
      "type": "paragraph",
      "page": 2,
      "bbox": [
        84.96,
        678.44,
        536.83,
        687.44
      ],
      "text": "Ministeries SZW, OCW en VWS plaatsvinden en daarna met de belangenorganisaties. Zonder dat er",
      "source": "text"
    },
    {
      "type": "paragraph",
      "page": 2,
      "bbox": [
        84.96,
        689.36,
        564.63,
        698.36
      ],
      "text": "vanuit de markt verdere druk ontstaat op een spoedige voortgang op het delen en implementeren van de",
      "source": "text"
    },
    {
      "type": "paragraph",
      "page": 2,
      "bbox": [
        84.96,
        700.27,
        268.0,
        709.27
      ],
      "text": "uitkomsten van het CEBEON-onderzoek.",
      "source": "text"
    },
    {
      "type": "paragraph",
      "page": 2,
      "bbox": [
        67.56,
        722.13,
        169.88,
        731.13
      ],
      "text": "7. Voortgang/vervolg",
      "source": "text"
    },
    {
      "type": "paragraph",
      "page": 2,
      "bbox": [
        84.96,
        733.05,
        539.17,
        742.05
      ],
      "text": "Mocht de Raad akkoord zijn met het genoemde voorstel, dan zullen de Beleidsregels Normbedragen",
      "source": "text"
    },
    {
      "type": "paragraph",
      "page": 2,
      "bbox": [
        84.96,
        743.96,
        554.98,
        752.96
      ],
      "text": "Voorzieningen worden aangepast. Deze Beleidsregels zullen op korte termijn aan u worden voorgelegd.",
      "source": "text"
    },
    {
      "type": "paragraph",
      "page": 2,
      "bbox": [
        84.96,
        755.01,
        541.67,
        764.01
      ],
      "text": "Er loopt nl. op dit moment ook een dialoog met het Ministerie van SZW over een maximering van de",
      "source": "text"
    },
    {
      "type": "paragraph",
      "page": 2,
      "bbox": [
        84.96,
        765.92,
        544.07,
        774.92
      ],
      "text": "eigen bijdrage taxikostenvergoeding, die eveneens een aanpassing van de Beleidsregels vergt. Beide",
      "source": "text"
    },
    {
      "type": "paragraph",
      "page": 2,
      "bbox": [
        84.96,
        776.84,
        320.18,
        785.84
      ],
      "text": "wijzigingen zullen dan gelijktijdig worden opgepakt.",
      "source": "text"
    },
    {
      "type": "paragraph",
      "page": 2,
      "bbox": [
        219.72,
        814.87,
        224.15,
        821.83
      ],
      "text": "2",
      "source": "text"
    },
    {
      "type": "paragraph",
      "page": 3,
      "bbox": [
        237.0,
        89.0,
        1497.0,
        114.0
      ],
      "text": "Daarnaast kan implementatie van de verhoging alvast worden voorbereid, zodat per i april a.s. een",
      "source": "ocr"
    },
    {
      "type": "paragraph",
      "page": 3,
      "bbox": [
        236.0,
        120.0,
        926.0,
        145.0
      ],
      "text": "soepele overgang van de facturering kan plaatsvinden.",
      "source": "ocr"
    },
    {
      "type": "paragraph",
      "page": 3,
      "bbox": [
        237.0,
        150.0,
        1288.0,
        175.0
      ],
      "text": "We gaan daarbij uit van de in de bijlage voorgestelde geïndexeerde normbedragen.",
      "source": "ocr"
    },
    {
      "type": "paragraph",
      "page": 3,
      "bbox": [
        138.0,
        233.0,
        464.0,
        253.0
      ],
      "text": "Vervolgtraject besluitvorming",
      "source": "ocr"
    },
    {
      "type": "paragraph",
      "page": 3,
      "bbox": [
        139.0,
        299.0,
        1538.0,
        324.0
      ],
      "text": "Na instemming door de Raad van Bestuur wordt een Wijzigingsbesluit Normbedragen Voorzieningen per 1 april",
      "source": "ocr"
    },
    {
      "type": "paragraph",
      "page": 3,
      "bbox": [
        139.0,
        329.0,
        1548.0,
        355.0
      ],
      "text": "2019 voorbereid. Dit Wijzigingsbesluit zal - inclusief overig te wijzigen aspecten - z.s.m. ter vaststelling aan de",
      "source": "ocr"
    },
    {
      "type": "paragraph",
      "page": 3,
      "bbox": [
        139.0,
        360.0,
        457.0,
        385.0
      ],
      "text": "Raad worden voorgelegd.",
      "source": "ocr"
    },
    {
      "type": "paragraph",
      "page": 3,
      "bbox": [
        139.0,
        431.0,
        412.0,
        451.0
      ],
      "text": "Financiële consequenties",
      "source": "ocr"
    },
    {
      "type": "paragraph",
      "page": 3,
      "bbox": [
        139.0,
        496.0,
        1358.0,
        521.0
      ],
      "text": "De verhoging is minimaal en kan uit het taakstellend budget Voorzieningen worden gefinancierd.",
      "source": "ocr"
    },
    {
      "type": "paragraph",
      "page": 3,
      "bbox": [
        139.0,
        566.0,
        410.0,
        585.0
      ],
      "text": "Personele consequenties",
      "source": "ocr"
    },
    {
      "type": "paragraph",
      "page": 3,
      "bbox": [
        139.0,
        632.0,
        203.0,
        651.0
      ],
      "text": "n.v.t.",
      "source": "ocr"
    },
    {
      "type": "paragraph",
      "page": 3,
      "bbox": [
        139.0,
        702.0,
        465.0,
        722.0
      ],
      "text": "Duurzaamheidsconsequenties",
      "source": "ocr"
    },
    {
      "type": "paragraph",
      "page": 3,
      "bbox": [
        139.0,
        768.0,
        203.0,
        787.0
      ],
      "text": "n.v.t.",
      "source": "ocr"
    },
    {
      "type": "paragraph",
      "page": 3,
      "bbox": [
        138.0,
        838.0,
        471.0,
        858.0
      ],
      "text": "Communicatie (intern/extern)",
      "source": "ocr"
    },
    {
      "type": "paragraph",
      "page": 3,
      "bbox": [
        139.0,
        902.0,
        1390.0,
        927.0
      ],
      "text": "Extern: Door publicatie in de Staatscourant en het informeren van de belangenorganisaties.",
      "source": "ocr"
    },
    {
      "type": "paragraph",
      "page": 3,
      "bbox": [
        336.0,
        934.0,
        1192.0,
        959.0
      ],
      "text": "Het Besluit en de aangepast Bijlage worden op uwv.nl gepubliceerd.",
      "source": "ocr"
    },
    {
      "type": "paragraph",
      "page": 3,
      "bbox": [
        138.0,
        963.0,
        653.0,
        983.0
      ],
      "text": "Intern: Via WIU en WERKbericht.",
      "source": "ocr"
    }
  ]
}
