{
  "source_id": "2023-11-20-woo-besluit-bezwaarproces-en-maatwerk/2023-11-20-2-handvest-maatwerk",
  "publication_slug": "2023-11-20-woo-besluit-bezwaarproces-en-maatwerk",
  "pdf_slug": "2023-11-20-2-handvest-maatwerk",
  "source_page_url": "https://www.uwv.nl/nl/wet-open-overheid/woo-publicaties/2023/woo-besluit-bezwaarproces-en-maatwerk",
  "pdf_url": "https://www.uwv.nl/assets-kai/files/34652e5a-b0c0-43b9-90fd-b633acfdaa35/2-handvest-maatwerk.pdf",
  "publication_title": "Woo-besluit Bezwaarproces en maatwerk",
  "publication_date": "2023-11-20T00:00:00Z",
  "publication_type": "WOO publicatie",
  "pdf_label": "Bijlage 2 Handvest maatwerk (PDF, 42 kB)",
  "retrieved_at": "2026-06-30T13:16:08+00:00",
  "sha256": "177bba3d89f75720a9b846c8b8a9f0bd517a33f831361be0fd8a8824ec1ed7f7",
  "page_count": 3,
  "ocr_used": false,
  "blocks": [
    {
      "type": "heading",
      "page": 1,
      "bbox": [
        74.96,
        72.15,
        325.46,
        102.15
      ],
      "text": "Handvest maatwerk",
      "source": "text"
    },
    {
      "type": "heading",
      "page": 1,
      "bbox": [
        70.96,
        129.67,
        323.64,
        149.67
      ],
      "text": "Een visie op maatwerk bij UWV",
      "source": "text"
    },
    {
      "type": "heading",
      "page": 1,
      "bbox": [
        431.26,
        182.85,
        771.45,
        200.85
      ],
      "text": "Allereerst, wat verstaan we onder maatwerk?",
      "source": "text"
    },
    {
      "type": "paragraph",
      "page": 1,
      "bbox": [
        60.96,
        185.0,
        363.37,
        199.0
      ],
      "text": "Bij UWV spannen we ons dagelijks in om burgers van",
      "source": "text"
    },
    {
      "type": "paragraph",
      "page": 1,
      "bbox": [
        60.96,
        201.01,
        393.0,
        215.01
      ],
      "text": "perspectief op werk en inkomen te voorzien. Meestal gaat",
      "source": "text"
    },
    {
      "type": "paragraph",
      "page": 1,
      "bbox": [
        60.96,
        217.01,
        383.75,
        231.01
      ],
      "text": "dit goed en krijgen burgers de passende dienstverlening",
      "source": "text"
    },
    {
      "type": "paragraph",
      "page": 1,
      "bbox": [
        443.02,
        230.46,
        493.76,
        242.46
      ],
      "text": "Maatwerk",
      "source": "text"
    },
    {
      "type": "paragraph",
      "page": 1,
      "bbox": [
        496.56,
        230.63,
        765.31,
        242.63
      ],
      "text": "is i) het onderkennen van bijzondere situaties die tot een",
      "source": "text"
    },
    {
      "type": "paragraph",
      "page": 1,
      "bbox": [
        60.96,
        233.01,
        369.19,
        247.01
      ],
      "text": "waar zij recht op hebben. En soms niet. UWV verstrekt",
      "source": "text"
    },
    {
      "type": "paragraph",
      "page": 1,
      "bbox": [
        443.02,
        245.63,
        713.98,
        257.63
      ],
      "text": "onbedoelde benadeling van de burger (kunnen) leiden en",
      "source": "text"
    },
    {
      "type": "paragraph",
      "page": 1,
      "bbox": [
        60.96,
        249.01,
        405.04,
        263.01
      ],
      "text": "maandelijks aan ruim één miljoen mensen een uitkering. Dit",
      "source": "text"
    },
    {
      "type": "paragraph",
      "page": 1,
      "bbox": [
        445.81,
        260.63,
        751.99,
        272.63
      ],
      "text": "ii) in dat geval de ruimte in de regels te benutten en te handelen",
      "source": "text"
    },
    {
      "type": "paragraph",
      "page": 1,
      "bbox": [
        60.96,
        265.01,
        401.51,
        279.01
      ],
      "text": "lukt alleen door met standaarden, processen en protocollen",
      "source": "text"
    },
    {
      "type": "paragraph",
      "page": 1,
      "bbox": [
        443.02,
        275.63,
        592.61,
        287.63
      ],
      "text": "naar de bedoeling van de regel.",
      "source": "text"
    },
    {
      "type": "paragraph",
      "page": 1,
      "bbox": [
        60.96,
        281.02,
        397.77,
        295.02
      ],
      "text": "te werken. Hier mogen we ook op vertrouwen. Er doen zich",
      "source": "text"
    },
    {
      "type": "paragraph",
      "page": 1,
      "bbox": [
        60.96,
        297.02,
        382.97,
        311.02
      ],
      "text": "echter altijd bijzondere situaties voor waar de standaard",
      "source": "text"
    },
    {
      "type": "paragraph",
      "page": 1,
      "bbox": [
        431.26,
        312.3,
        746.68,
        323.3
      ],
      "text": "In andere woorden passen we maatwerk toe als standaardprotocollen",
      "source": "text"
    },
    {
      "type": "paragraph",
      "page": 1,
      "bbox": [
        60.96,
        313.02,
        383.37,
        327.02
      ],
      "text": "niet volstaat of zelfs niet voor is geschreven. Burgers (en",
      "source": "text"
    },
    {
      "type": "paragraph",
      "page": 1,
      "bbox": [
        431.26,
        327.3,
        744.56,
        338.3
      ],
      "text": "niet voldoen en deze standaard aanpak (gelijke behandeling) leidt tot",
      "source": "text"
    },
    {
      "type": "paragraph",
      "page": 1,
      "bbox": [
        60.96,
        329.02,
        389.29,
        343.02
      ],
      "text": "werkgevers) belanden dan tussen wal en schip. We willen",
      "source": "text"
    },
    {
      "type": "paragraph",
      "page": 1,
      "bbox": [
        431.26,
        342.31,
        760.33,
        353.31
      ],
      "text": "een onbedoelde benadeling van de burger. Maatwerk begint met wat we",
      "source": "text"
    },
    {
      "type": "paragraph",
      "page": 1,
      "bbox": [
        60.96,
        345.02,
        371.4,
        359.02
      ],
      "text": "onze dienstverlening op dit punt zichtbaar verbeteren.",
      "source": "text"
    },
    {
      "type": "paragraph",
      "page": 1,
      "bbox": [
        542.41,
        357.31,
        777.77,
        368.31
      ],
      "text": "noemen, het gevoel bij de medewerker “dat hier iets",
      "source": "text"
    },
    {
      "type": "paragraph",
      "page": 1,
      "bbox": [
        431.26,
        357.31,
        539.77,
        368.39
      ],
      "text": "“professionele buikpijn”",
      "source": "text"
    },
    {
      "type": "paragraph",
      "page": 1,
      "bbox": [
        60.96,
        361.03,
        376.95,
        375.03
      ],
      "text": "De samenleving vraagt ook van ons dat we als publieke",
      "source": "text"
    },
    {
      "type": "paragraph",
      "page": 1,
      "bbox": [
        431.26,
        372.32,
        776.54,
        383.32
      ],
      "text": "niet klopt en/of Het gaat over het “inleven” of",
      "source": "text"
    },
    {
      "type": "paragraph",
      "page": 1,
      "bbox": [
        619.94,
        372.32,
        641.58,
        383.39
      ],
      "text": "zijn”.",
      "source": "text"
    },
    {
      "type": "paragraph",
      "page": 1,
      "bbox": [
        503.59,
        372.39,
        617.44,
        383.39
      ],
      "text": "dit niet de bedoeling kan",
      "source": "text"
    },
    {
      "type": "paragraph",
      "page": 1,
      "bbox": [
        60.96,
        377.03,
        356.56,
        391.03
      ],
      "text": "dienstverlener meer de menselijke maat toepassen.",
      "source": "text"
    },
    {
      "type": "paragraph",
      "page": 1,
      "bbox": [
        431.26,
        387.32,
        775.42,
        398.32
      ],
      "text": "de regel past bij de situatie of in de praktijk anders uitpakt dan de bedoeling",
      "source": "text"
    },
    {
      "type": "paragraph",
      "page": 1,
      "bbox": [
        60.96,
        393.03,
        269.18,
        407.03
      ],
      "text": "Maatwerk is hier een onderdeel van.",
      "source": "text"
    },
    {
      "type": "paragraph",
      "page": 1,
      "bbox": [
        431.26,
        402.32,
        760.21,
        413.32
      ],
      "text": "van de wet- en regelgeving. Veelal gaat het dan over situaties waarin ons",
      "source": "text"
    },
    {
      "type": "paragraph",
      "page": 1,
      "bbox": [
        431.26,
        417.33,
        780.64,
        428.33
      ],
      "text": "besluit voor de burger onevenredig uitpakt. Dit vraagt om inlevingsvermogen",
      "source": "text"
    },
    {
      "type": "paragraph",
      "page": 1,
      "bbox": [
        431.26,
        432.33,
        774.53,
        443.33
      ],
      "text": "en empathie voor de burger én een zelfbewustzijn over onze rol als publieke",
      "source": "text"
    },
    {
      "type": "paragraph",
      "page": 1,
      "bbox": [
        431.26,
        447.34,
        763.34,
        458.34
      ],
      "text": "dienstverlener. We moedigen de organisatie aan tot zelfbewust handelen.",
      "source": "text"
    },
    {
      "type": "paragraph",
      "page": 1,
      "bbox": [
        431.26,
        462.34,
        780.16,
        473.34
      ],
      "text": "Voor een goed begrip, willen we benadrukken dat lang niet alles neerkomt op",
      "source": "text"
    },
    {
      "type": "paragraph",
      "page": 1,
      "bbox": [
        431.26,
        477.34,
        776.74,
        488.34
      ],
      "text": "maatwerk. We kunnen en mogen vertrouwen op hoe we in de regel ons werk",
      "source": "text"
    },
    {
      "type": "paragraph",
      "page": 1,
      "bbox": [
        431.26,
        492.35,
        780.84,
        503.35
      ],
      "text": "doen. Maatwerk vergt dat we alert zijn en blijven op de uitzonderingen op die",
      "source": "text"
    },
    {
      "type": "paragraph",
      "page": 1,
      "bbox": [
        431.26,
        507.35,
        456.31,
        518.35
      ],
      "text": "regel.",
      "source": "text"
    },
    {
      "type": "paragraph",
      "page": 1,
      "bbox": [
        41.44,
        547.53,
        135.56,
        557.53
      ],
      "text": "1 | Handvest maatwerk",
      "source": "text"
    },
    {
      "type": "heading",
      "page": 1,
      "bbox": [
        26.0,
        571.78,
        108.57,
        588.89
      ],
      "text": "MAATWERK",
      "source": "text"
    },
    {
      "type": "heading",
      "page": 2,
      "bbox": [
        60.96,
        57.09,
        223.72,
        75.09
      ],
      "text": "Van wie is maatwerk?",
      "source": "text"
    },
    {
      "type": "paragraph",
      "page": 2,
      "bbox": [
        60.96,
        87.3,
        776.03,
        98.34
      ],
      "text": "Maatwerk is Dit betekent dat elke divisie, elk district maatwerk met verstrekkende gevolgen, bijvoorbeeld omdat grote groepen",
      "source": "text"
    },
    {
      "type": "paragraph",
      "page": 2,
      "bbox": [
        156.25,
        87.3,
        197.38,
        98.38
      ],
      "text": "allemaal.",
      "source": "text"
    },
    {
      "type": "paragraph",
      "page": 2,
      "bbox": [
        118.81,
        87.38,
        153.76,
        98.38
      ],
      "text": "van ons",
      "source": "text"
    },
    {
      "type": "paragraph",
      "page": 2,
      "bbox": [
        60.96,
        102.3,
        774.45,
        113.34
      ],
      "text": "en elk team aan de slag gaat met maatwerkvraagstukken klein en groot. burgers hiermee te maken krijgen, vindt de afstemming en besluitvorming",
      "source": "text"
    },
    {
      "type": "paragraph",
      "page": 2,
      "bbox": [
        60.96,
        117.31,
        758.53,
        128.35
      ],
      "text": "We zien maatwerk als een regulier onderdeel van onze dienstverlening. plaats op het niveau in de organisatie dat de verantwoordelijkheid kan",
      "source": "text"
    },
    {
      "type": "paragraph",
      "page": 2,
      "bbox": [
        60.96,
        132.31,
        769.25,
        143.35
      ],
      "text": "Daarnaast ontmoeten we elkaar ook in de om nemen voor het besluit. Dat kan bijvoorbeeld de districtsmanager zijn, de",
      "source": "text"
    },
    {
      "type": "paragraph",
      "page": 2,
      "bbox": [
        251.65,
        132.39,
        326.31,
        143.39
      ],
      "text": "Maatwerkplaats",
      "source": "text"
    },
    {
      "type": "paragraph",
      "page": 2,
      "bbox": [
        60.96,
        147.32,
        400.95,
        158.32
      ],
      "text": "maatwerkvraagstukken te behandelen en hiervan te leren. Het begint bij de",
      "source": "text"
    },
    {
      "type": "paragraph",
      "page": 2,
      "bbox": [
        440.74,
        147.35,
        607.77,
        158.35
      ],
      "text": "directie of zelfs de Raad van Bestuur.",
      "source": "text"
    },
    {
      "type": "paragraph",
      "page": 2,
      "bbox": [
        60.96,
        162.32,
        397.19,
        173.32
      ],
      "text": "medewerker die zich afvraagt of de situatie van deze burger om maatwerk",
      "source": "text"
    },
    {
      "type": "paragraph",
      "page": 2,
      "bbox": [
        60.96,
        177.32,
        388.39,
        188.32
      ],
      "text": "vraagt. Essentieel is dat deze medewerker de ruimte krijgt en ervaart om",
      "source": "text"
    },
    {
      "type": "heading",
      "page": 2,
      "bbox": [
        440.74,
        178.89,
        753.13,
        196.89
      ],
      "text": "Binnen welk kader nemen we het besluit?",
      "source": "text"
    },
    {
      "type": "paragraph",
      "page": 2,
      "bbox": [
        60.96,
        192.33,
        284.75,
        203.33
      ],
      "text": "maatwerk te bewerkstelligen. We bevorderen een",
      "source": "text"
    },
    {
      "type": "paragraph",
      "page": 2,
      "bbox": [
        287.39,
        192.4,
        385.57,
        203.4
      ],
      "text": "cultuur van veiligheid",
      "source": "text"
    },
    {
      "type": "paragraph",
      "page": 2,
      "bbox": [
        132.31,
        207.3,
        753.48,
        218.33
      ],
      "text": "waarin je een fout mag maken en we hiervan leren. We Bij het realiseren van maatwerk moedigen we de medewerker aan de",
      "source": "text"
    },
    {
      "type": "paragraph",
      "page": 2,
      "bbox": [
        74.71,
        207.33,
        129.67,
        218.41
      ],
      "text": "vertrouwen,",
      "source": "text"
    },
    {
      "type": "paragraph",
      "page": 2,
      "bbox": [
        60.96,
        207.41,
        72.21,
        218.41
      ],
      "text": "en",
      "source": "text"
    },
    {
      "type": "paragraph",
      "page": 2,
      "bbox": [
        60.96,
        222.3,
        775.11,
        233.34
      ],
      "text": "bevorderen dat we op alle niveaus in de organisatie met elkaar in gesprek ruimte te zoeken en te nemen om het “net iets anders te doen” in situaties",
      "source": "text"
    },
    {
      "type": "paragraph",
      "page": 2,
      "bbox": [
        60.96,
        237.31,
        769.99,
        248.34
      ],
      "text": "gaan over maatwerk: over de aanpak, de dilemma’s en de besluiten die die daarom vragen. Essentieel is dat we alle relevante feiten en belangen",
      "source": "text"
    },
    {
      "type": "paragraph",
      "page": 2,
      "bbox": [
        60.96,
        252.31,
        763.66,
        263.34
      ],
      "text": "we nemen. We onderkennen dat we nog het nodige kunnen leren over in kaart brengen en goed wegen. De ervaring leert dat een oplossing op",
      "source": "text"
    },
    {
      "type": "paragraph",
      "page": 2,
      "bbox": [
        60.96,
        267.32,
        762.36,
        278.35
      ],
      "text": "maatwerk. Op de leidinggevende rust de belangrijke verantwoordelijkheid maat veelal binnen de wet- en regelgeving is te vinden. Uitgangspunt is",
      "source": "text"
    },
    {
      "type": "paragraph",
      "page": 2,
      "bbox": [
        440.74,
        282.32,
        759.31,
        293.32
      ],
      "text": "dan ook dat het maatwerkbesluit is. Dat wil zeggen dat het",
      "source": "text"
    },
    {
      "type": "paragraph",
      "page": 2,
      "bbox": [
        60.96,
        282.35,
        642.44,
        293.4
      ],
      "text": "om maatwerk in tijd, ruimte en middelen te faciliteren. Vertrouwen in de rechtmatig",
      "source": "text"
    },
    {
      "type": "paragraph",
      "page": 2,
      "bbox": [
        440.74,
        297.32,
        777.55,
        308.32
      ],
      "text": "besluit past binnen de (bedoeling van de) wet- en regelgeving, rechtspraak",
      "source": "text"
    },
    {
      "type": "paragraph",
      "page": 2,
      "bbox": [
        60.96,
        297.36,
        291.94,
        308.36
      ],
      "text": "deskundigheid van de medewerker(s) staat voorop.",
      "source": "text"
    },
    {
      "type": "paragraph",
      "page": 2,
      "bbox": [
        440.74,
        312.33,
        760.95,
        323.33
      ],
      "text": "en ongeschreven recht zoals de rechtsbeginselen. We denken soms dat",
      "source": "text"
    },
    {
      "type": "paragraph",
      "page": 2,
      "bbox": [
        440.74,
        327.33,
        764.82,
        338.33
      ],
      "text": "er geen ruimte is, terwijl we die ruimte wel kunnen opzoeken en kunnen",
      "source": "text"
    },
    {
      "type": "heading",
      "page": 2,
      "bbox": [
        60.96,
        328.89,
        149.68,
        346.89
      ],
      "text": "Wie beslist?",
      "source": "text"
    },
    {
      "type": "paragraph",
      "page": 2,
      "bbox": [
        440.74,
        342.34,
        754.8,
        353.34
      ],
      "text": "nemen. Het komt ook aan op durf: zoek deze grenzen op en maak een",
      "source": "text"
    },
    {
      "type": "paragraph",
      "page": 2,
      "bbox": [
        60.96,
        357.3,
        727.45,
        368.34
      ],
      "text": "Voor het realiseren van maatwerk bestaat geen blauwdruk. Wel zijn er uitzondering als dat nodig is. Bijzondere aandacht verdienen de",
      "source": "text"
    },
    {
      "type": "paragraph",
      "page": 2,
      "bbox": [
        730.09,
        357.42,
        774.88,
        368.42
      ],
      "text": "algemene",
      "source": "text"
    },
    {
      "type": "paragraph",
      "page": 2,
      "bbox": [
        60.96,
        372.3,
        773.72,
        383.34
      ],
      "text": "een aantal vuistregels. Uitgangspunt is dat als grondslag voor het maatwerk. Deze",
      "source": "text"
    },
    {
      "type": "paragraph",
      "page": 2,
      "bbox": [
        255.72,
        372.38,
        596.01,
        383.42
      ],
      "text": "de medewerker binnen zijn beginselen van behoorlijk bestuur",
      "source": "text"
    },
    {
      "type": "paragraph",
      "page": 2,
      "bbox": [
        104.28,
        387.31,
        769.55,
        398.35
      ],
      "text": "tot een maatwerkbesluit komt. Belangrijk is dat maatwerk in de beginselen beschrijven hoe wij ons als overheidsorgaan gedragen en hoe",
      "source": "text"
    },
    {
      "type": "paragraph",
      "page": 2,
      "bbox": [
        60.96,
        387.38,
        101.64,
        398.38
      ],
      "text": "mandaat",
      "source": "text"
    },
    {
      "type": "paragraph",
      "page": 2,
      "bbox": [
        60.96,
        402.31,
        378.91,
        413.31
      ],
      "text": "regel een gezamenlijk besluit is: bespreek en bepaal met collega’s, staf",
      "source": "text"
    },
    {
      "type": "paragraph",
      "page": 2,
      "bbox": [
        440.74,
        402.35,
        752.11,
        413.35
      ],
      "text": "wij tot onze besluiten komen. De algemene beginselen van behoorlijk",
      "source": "text"
    },
    {
      "type": "paragraph",
      "page": 2,
      "bbox": [
        60.96,
        417.32,
        380.83,
        428.32
      ],
      "text": "en/of je leidinggevende wat nodig is om tot een goed gedragen besluit",
      "source": "text"
    },
    {
      "type": "paragraph",
      "page": 2,
      "bbox": [
        440.74,
        417.36,
        772.93,
        428.36
      ],
      "text": "bestuur zijn met name van belang als de standaardbenadering onbedoeld",
      "source": "text"
    },
    {
      "type": "paragraph",
      "page": 2,
      "bbox": [
        60.96,
        432.32,
        372.91,
        443.32
      ],
      "text": "te komen. Bij maatwerk binnen de standaarden en regelgeving kan je",
      "source": "text"
    },
    {
      "type": "paragraph",
      "page": 2,
      "bbox": [
        440.74,
        432.36,
        782.02,
        443.36
      ],
      "text": "en disproportioneel uitpakt. We lichten er een drietal belangrijke beginselen",
      "source": "text"
    },
    {
      "type": "paragraph",
      "page": 2,
      "bbox": [
        60.96,
        447.32,
        369.92,
        458.32
      ],
      "text": "(na afstemming) doorgaans zelf het besluit nemen. Zo’n situatie is te",
      "source": "text"
    },
    {
      "type": "paragraph",
      "page": 2,
      "bbox": [
        440.74,
        447.36,
        455.22,
        458.36
      ],
      "text": "uit:",
      "source": "text"
    },
    {
      "type": "paragraph",
      "page": 2,
      "bbox": [
        60.96,
        462.33,
        380.21,
        473.33
      ],
      "text": "zien als een probleem binnen de regels dat je met maatwerk oplost. Bij",
      "source": "text"
    },
    {
      "type": "paragraph",
      "page": 2,
      "bbox": [
        60.96,
        477.33,
        381.05,
        488.33
      ],
      "text": "problemen van de regel (beleid, wet- en regelgeving) vindt afstemming",
      "source": "text"
    },
    {
      "type": "paragraph",
      "page": 2,
      "bbox": [
        440.74,
        477.36,
        761.75,
        488.36
      ],
      "text": "Het dat we kunnen toepassen als de gevolgen",
      "source": "text"
    },
    {
      "type": "paragraph",
      "page": 2,
      "bbox": [
        459.38,
        477.36,
        570.39,
        488.44
      ],
      "text": "evenredigheidsbeginsel:",
      "source": "text"
    },
    {
      "type": "paragraph",
      "page": 2,
      "bbox": [
        60.96,
        492.34,
        186.25,
        503.34
      ],
      "text": "en besluitvorming plaats op",
      "source": "text"
    },
    {
      "type": "paragraph",
      "page": 2,
      "bbox": [
        188.89,
        492.36,
        769.57,
        503.41
      ],
      "text": "het niveau dat past bij de impact van het van een besluit wegens bijzondere omstandigheden onevenredig zijn ten",
      "source": "text"
    },
    {
      "type": "paragraph",
      "page": 2,
      "bbox": [
        97.15,
        507.34,
        391.41,
        518.34
      ],
      "text": "In de regel is dan betrokkenheid van de leidinggevende nodig. Bij",
      "source": "text"
    },
    {
      "type": "paragraph",
      "page": 2,
      "bbox": [
        60.96,
        507.34,
        94.51,
        518.42
      ],
      "text": "besluit.",
      "source": "text"
    },
    {
      "type": "paragraph",
      "page": 2,
      "bbox": [
        440.74,
        507.37,
        598.07,
        518.37
      ],
      "text": "opzichte van het doel van de regel.",
      "source": "text"
    },
    {
      "type": "paragraph",
      "page": 2,
      "bbox": [
        41.44,
        547.53,
        135.62,
        557.53
      ],
      "text": "2 | Handvest maatwerk",
      "source": "text"
    },
    {
      "type": "paragraph",
      "page": 3,
      "bbox": [
        60.96,
        72.3,
        772.58,
        83.3
      ],
      "text": "Het dat kortweg inhoudt dat de burger UWV mag kunnen op die manier zien op welke manier voor welke casussen mogelijk",
      "source": "text"
    },
    {
      "type": "paragraph",
      "page": 3,
      "bbox": [
        79.61,
        72.3,
        178.28,
        83.38
      ],
      "text": "vertrouwensbeginsel:",
      "source": "text"
    },
    {
      "type": "paragraph",
      "page": 3,
      "bbox": [
        60.96,
        87.3,
        755.43,
        98.3
      ],
      "text": "houden aan een toezegging. maatwerk gerealiseerd kan worden (en welke situaties zich niet lenen",
      "source": "text"
    },
    {
      "type": "paragraph",
      "page": 3,
      "bbox": [
        440.94,
        102.31,
        763.75,
        113.31
      ],
      "text": "voor maatwerk!). Ook kunnen we binnen UWV monitoren hoe maatwerk",
      "source": "text"
    },
    {
      "type": "paragraph",
      "page": 3,
      "bbox": [
        60.96,
        117.3,
        741.58,
        128.31
      ],
      "text": "Het dat meebrengt dat UWV gelijke gevallen gelijk geleverd wordt, kunnen signalen van knelpunten breed gedeeld en",
      "source": "text"
    },
    {
      "type": "paragraph",
      "page": 3,
      "bbox": [
        79.61,
        117.3,
        170.5,
        128.38
      ],
      "text": "gelijkheidsbeginsel:",
      "source": "text"
    },
    {
      "type": "paragraph",
      "page": 3,
      "bbox": [
        60.96,
        132.3,
        779.51,
        143.32
      ],
      "text": "behandelt en ongelijke gevallen in de mate van ongelijkheid. aangepakt worden om beleid en wetgeving te verbeteren, en kan UWV zich",
      "source": "text"
    },
    {
      "type": "paragraph",
      "page": 3,
      "bbox": [
        60.96,
        147.31,
        630.63,
        158.32
      ],
      "text": "De wetsgeschiedenis geeft inzicht in de bedoeling van de regel. We ook verantwoorden naar de maatschappij.",
      "source": "text"
    },
    {
      "type": "paragraph",
      "page": 3,
      "bbox": [
        60.96,
        162.31,
        377.47,
        173.31
      ],
      "text": "maken de afweging en de motivering van het maatwerk inzichtelijk en",
      "source": "text"
    },
    {
      "type": "paragraph",
      "page": 3,
      "bbox": [
        60.96,
        177.32,
        400.4,
        188.32
      ],
      "text": "navolgbaar, zodat we kunnen zien hoe we tot dit besluit zijn gekomen en in",
      "source": "text"
    },
    {
      "type": "heading",
      "page": 3,
      "bbox": [
        440.94,
        178.89,
        511.94,
        196.89
      ],
      "text": "En verder",
      "source": "text"
    },
    {
      "type": "paragraph",
      "page": 3,
      "bbox": [
        60.96,
        192.32,
        393.07,
        203.32
      ],
      "text": "vergelijkbare gevallen op dezelfde manier kunnen handelen. Dit voorkomt",
      "source": "text"
    },
    {
      "type": "paragraph",
      "page": 3,
      "bbox": [
        60.96,
        207.3,
        778.29,
        218.32
      ],
      "text": "willekeur. Maatwerk is het onderkennen van complexiteit en het centraler stellen van",
      "source": "text"
    },
    {
      "type": "paragraph",
      "page": 3,
      "bbox": [
        440.94,
        222.3,
        781.48,
        233.3
      ],
      "text": "de burger. De manier waarop we maatwerk realiseren laat zich per definitie",
      "source": "text"
    },
    {
      "type": "paragraph",
      "page": 3,
      "bbox": [
        440.94,
        237.31,
        764.44,
        248.31
      ],
      "text": "niet van a tot z voorschrijven. Een open blik en creativiteit staan voorop.",
      "source": "text"
    },
    {
      "type": "heading",
      "page": 3,
      "bbox": [
        60.96,
        238.89,
        207.03,
        256.89
      ],
      "text": "De Maatwerkplaats",
      "source": "text"
    },
    {
      "type": "paragraph",
      "page": 3,
      "bbox": [
        440.94,
        252.31,
        765.77,
        263.31
      ],
      "text": "Maatwerk is ook een cultuur waarin we met elkaar het gesprek aangaan",
      "source": "text"
    },
    {
      "type": "paragraph",
      "page": 3,
      "bbox": [
        60.96,
        267.3,
        774.52,
        278.32
      ],
      "text": "De Maatwerkplaats is een netwerk van praktijkprofessionals die bij elkaar over de dilemma’s waarin regels, uitvoering en de belangen van de burger",
      "source": "text"
    },
    {
      "type": "paragraph",
      "page": 3,
      "bbox": [
        60.96,
        282.3,
        766.28,
        293.32
      ],
      "text": "worden gebracht om gezamenlijk tot een gedragen besluit te komen. schuren. Hier leren we van en zodoende ontwikkelen we een gedeeld en",
      "source": "text"
    },
    {
      "type": "paragraph",
      "page": 3,
      "bbox": [
        60.96,
        297.31,
        755.81,
        308.32
      ],
      "text": "Daarnaast leren we hiervan om waar mogelijk toekomstige situaties te doorleefd begrip van wat we onder maatwerk verstaan. We gebruiken",
      "source": "text"
    },
    {
      "type": "paragraph",
      "page": 3,
      "bbox": [
        60.96,
        312.31,
        764.31,
        323.33
      ],
      "text": "voorkomen. Deze Maatwerkplaatsen zijn op ieder moment in elke situatie deze inzichten in onze gesprekken met het Ministerie van Sociale Zaken",
      "source": "text"
    },
    {
      "type": "paragraph",
      "page": 3,
      "bbox": [
        60.96,
        327.32,
        768.11,
        338.33
      ],
      "text": "te benaderen voor het behandelen van complexe maatwerkvraagstukken. en Werkgelegenheid om tot betere wet- en regelgeving te komen. Vanuit",
      "source": "text"
    },
    {
      "type": "paragraph",
      "page": 3,
      "bbox": [
        60.96,
        342.32,
        776.98,
        353.34
      ],
      "text": "De collega van de Maatwerkplaats begeleidt het proces van afstemming en die ruimte die wij zien en het vertrouwen in onze professionals, denken wij",
      "source": "text"
    },
    {
      "type": "paragraph",
      "page": 3,
      "bbox": [
        60.96,
        357.32,
        762.05,
        368.34
      ],
      "text": "besluitvorming. De indiener blijft de eigenaar van de casus en het besluit deze slag te kunnen maken. Om het maatwerk te bevorderen reiken we",
      "source": "text"
    },
    {
      "type": "paragraph",
      "page": 3,
      "bbox": [
        60.96,
        372.33,
        766.53,
        383.34
      ],
      "text": "wordt binnen het mandaat uitgevoerd. De Maatwerkplaats vervult verder algemene kaders aan, in de vorm van een handreiking waar men terecht",
      "source": "text"
    },
    {
      "type": "paragraph",
      "page": 3,
      "bbox": [
        60.96,
        387.33,
        763.31,
        398.35
      ],
      "text": "een belangrijke rol als aanjager van het denken, leren en handelen in de kan met maatwerkvraagstukken en een uiteenzetting van het juridische",
      "source": "text"
    },
    {
      "type": "paragraph",
      "page": 3,
      "bbox": [
        60.96,
        402.34,
        224.72,
        413.34
      ],
      "text": "organisatie op het thema maatwerk.",
      "source": "text"
    },
    {
      "type": "paragraph",
      "page": 3,
      "bbox": [
        440.94,
        402.35,
        770.15,
        413.35
      ],
      "text": "kader voor het onderbouwen van het maatwerk. En we gaan in alle lagen",
      "source": "text"
    },
    {
      "type": "paragraph",
      "page": 3,
      "bbox": [
        440.94,
        417.36,
        768.94,
        428.36
      ],
      "text": "van de organisatie en in breed verband de dialoog aan over de betekenis",
      "source": "text"
    },
    {
      "type": "paragraph",
      "page": 3,
      "bbox": [
        440.94,
        432.36,
        696.24,
        443.36
      ],
      "text": "van maatwerk voor ons werk als publieke dienstverlener.",
      "source": "text"
    },
    {
      "type": "heading",
      "page": 3,
      "bbox": [
        60.96,
        433.89,
        239.83,
        451.89
      ],
      "text": "Balans en transparantie",
      "source": "text"
    },
    {
      "type": "paragraph",
      "page": 3,
      "bbox": [
        60.96,
        462.3,
        392.66,
        473.3
      ],
      "text": "Om te zorgen dat we leren van maatwerk, en ook willekeur te voorkomen,",
      "source": "text"
    },
    {
      "type": "paragraph",
      "page": 3,
      "bbox": [
        60.96,
        477.3,
        363.85,
        488.3
      ],
      "text": "wordt maatwerk altijd zorgvuldig vastgelegd en actief gedeeld met",
      "source": "text"
    },
    {
      "type": "paragraph",
      "page": 3,
      "bbox": [
        60.96,
        492.31,
        372.26,
        503.31
      ],
      "text": "collega’s van verschillende disciplines. Met het oog op privacy dienen",
      "source": "text"
    },
    {
      "type": "paragraph",
      "page": 3,
      "bbox": [
        60.96,
        507.31,
        371.67,
        518.31
      ],
      "text": "de persoonsgegevens van de betrokken burger verwijderd te zijn. We",
      "source": "text"
    },
    {
      "type": "paragraph",
      "page": 3,
      "bbox": [
        41.44,
        547.53,
        135.62,
        557.53
      ],
      "text": "3 | Handvest maatwerk",
      "source": "text"
    }
  ]
}
